{"id":685,"name":"8А","info":null,"head_teacher":{"id":1134,"full_name":"Козлачкова Виола Тихоновна","birthday":"1987-08-19","tel":null,"email":null,"dnevnik_id":1000000000068,"dnevnik_person_id":1000000000072,"job":"Учитель, Редактор"},"year":2018,"dnevnik_id":1000000000000000037,"periods_count":4,"final_class":{"id":665,"name":"9А","info":null,"head_teacher":1134,"year":2019,"dnevnik_id":1000000000000000017,"periods_count":4,"final_class":null},"students":[{"id":11109,"full_name":"Артемьева Соня Юлиановна","birthday":"2004-07-09","tel":"+7-(909)-253-62-98","email":null,"dnevnik_id":1000000000330,"dnevnik_person_id":1000000000414,"info":null,"entered":null,"leaved":null,"parents":null,"class":665,"previous_classes":[685,708]},{"id":10980,"full_name":"Басырова Павлина Власовна","birthday":"2004-07-14","tel":null,"email":null,"dnevnik_id":1000000000242,"dnevnik_person_id":1000000000285,"info":null,"entered":null,"leaved":null,"parents":null,"class":665,"previous_classes":[685]},{"id":11050,"full_name":"Блохина Кристина Елизаровна","birthday":"2004-08-13","tel":null,"email":null,"dnevnik_id":1000000000289,"dnevnik_person_id":1000000000355,"info":null,"entered":null,"leaved":null,"parents":null,"class":665,"previous_classes":[685,708]},{"id":10881,"full_name":"Богословская Алтын Димитриевна","birthday":"2004-09-19","tel":null,"email":null,"dnevnik_id":1000000000172,"dnevnik_person_id":1000000000186,"info":null,"entered":null,"leaved":null,"parents":null,"class":665,"previous_classes":[685,708]},{"id":11100,"full_name":"Бондарев Родион Дмитриевич","birthday":"2004-01-21","tel":"+7-(968)-405-57-14","email":null,"dnevnik_id":null,"dnevnik_person_id":1000000000405,"info":null,"entered":null,"leaved":null,"parents":null,"class":665,"previous_classes":[685,708]},{"id":10801,"full_name":"Буркатовская Амина Дмитриевна","birthday":"2004-02-29","tel":null,"email":null,"dnevnik_id":1000000000111,"dnevnik_person_id":1000000000106,"info":null,"entered":null,"leaved":null,"parents":null,"class":665,"previous_classes":[685,708]},{"id":11119,"full_name":"Валетова Шакира Вадимовна","birthday":"2004-12-18","tel":null,"email":null,"dnevnik_id":1000000000337,"dnevnik_person_id":1000000000424,"info":null,"entered":null,"leaved":null,"parents":null,"class":665,"previous_classes":[685]},{"id":11167,"full_name":"Григорович Семён Егорович","birthday":"2004-04-19","tel":null,"email":null,"dnevnik_id":1000000000365,"dnevnik_person_id":1000000000472,"info":null,"entered":null,"leaved":null,"parents":null,"class":665,"previous_classes":[685]},{"id":10969,"full_name":"Зимина Алексия Елизаровна","birthday":"2003-01-05","tel":null,"email":null,"dnevnik_id":1000000000235,"dnevnik_person_id":1000000000274,"info":null,"entered":null,"leaved":null,"parents":null,"class":665,"previous_classes":[685]},{"id":11045,"full_name":"Кормильцева Эльмира Гавриловна","birthday":"2004-09-06","tel":null,"email":null,"dnevnik_id":1000000000285,"dnevnik_person_id":1000000000350,"info":null,"entered":null,"leaved":null,"parents":null,"class":665,"previous_classes":[685]},{"id":10904,"full_name":"Мухина Аида Владиленовна","birthday":"2004-01-09","tel":null,"email":null,"dnevnik_id":1000000000187,"dnevnik_person_id":1000000000209,"info":null,"entered":null,"leaved":null,"parents":null,"class":665,"previous_classes":[685]},{"id":10986,"full_name":"Обухова Нонна Александровна","birthday":"2004-05-27","tel":null,"email":null,"dnevnik_id":1000000000246,"dnevnik_person_id":1000000000291,"info":null,"entered":null,"leaved":null,"parents":null,"class":665,"previous_classes":[685,708]},{"id":11997,"full_name":"Расторгуева Эстер Валентиновна","birthday":null,"tel":null,"email":null,"dnevnik_id":null,"dnevnik_person_id":1000000001302,"info":null,"entered":null,"leaved":null,"parents":null,"class":685,"previous_classes":[708]},{"id":10963,"full_name":"Розанова Анжелика Давидовна","birthday":"2005-03-12","tel":"+7-(909)-067-44-33","email":null,"dnevnik_id":1000000000230,"dnevnik_person_id":1000000000268,"info":null,"entered":null,"leaved":null,"parents":null,"class":665,"previous_classes":[685,708]},{"id":11175,"full_name":"Садур Потап Ефимович","birthday":"2004-09-02","tel":"+7-(929)-327-38-08","email":null,"dnevnik_id":1000000000370,"dnevnik_person_id":1000000000480,"info":null,"entered":null,"leaved":null,"parents":null,"class":665,"previous_classes":[685,708]},{"id":10830,"full_name":"Сотников Лука Брониславович","birthday":"2004-02-11","tel":"+7-(960)-745-76-25","email":null,"dnevnik_id":1000000000134,"dnevnik_person_id":1000000000135,"info":null,"entered":null,"leaved":null,"parents":null,"class":665,"previous_classes":[685,708]},{"id":11005,"full_name":"Федулина Алевтина Германовна","birthday":"2004-04-24","tel":"+7-(919)-364-66-49","email":"liechtenstein1897@example.org","dnevnik_id":1000000000259,"dnevnik_person_id":1000000000310,"info":null,"entered":null,"leaved":null,"parents":null,"class":665,"previous_classes":[685,708]},{"id":11169,"full_name":"Шашкова Корнелия Харлампьевна","birthday":"2004-05-04","tel":null,"email":null,"dnevnik_id":1000000000367,"dnevnik_person_id":1000000000474,"info":null,"entered":null,"leaved":null,"parents":null,"class":665,"previous_classes":[685,708]},{"id":11170,"full_name":"Щепа Всеволод Адрианович","birthday":"2004-06-15","tel":null,"email":null,"dnevnik_id":1000000000368,"dnevnik_person_id":1000000000475,"info":null,"entered":null,"leaved":null,"parents":null,"class":665,"previous_classes":[685]},{"id":11068,"full_name":"Щербакова Малика Анатольевна","birthday":"2003-12-31","tel":null,"email":null,"dnevnik_id":1000000000300,"dnevnik_person_id":1000000000373,"info":null,"entered":null,"leaved":null,"parents":null,"class":665,"previous_classes":[685]}],"periods":[{"id":205,"num":1,"year":2018,"dnevnik_id":1000000000000000007},{"id":206,"num":2,"year":2018,"dnevnik_id":1000000000000000008},{"id":207,"num":3,"year":2018,"dnevnik_id":1000000000000000009},{"id":208,"num":4,"year":2018,"dnevnik_id":1000000000000000010}],"horizontal_classes":[{"id":685,"name":"8А","info":null,"head_teacher":1134,"year":2018,"dnevnik_id":1000000000000000037,"periods_count":4,"final_class":665},{"id":686,"name":"8Б","info":null,"head_teacher":1087,"year":2018,"dnevnik_id":1000000000000000038,"periods_count":4,"final_class":666}],"vertical_classes":[{"id":665,"name":"9А","info":null,"head_teacher":1134,"year":2019,"dnevnik_id":1000000000000000017,"periods_count":4,"final_class":null},{"id":685,"name":"8А","info":null,"head_teacher":1134,"year":2018,"dnevnik_id":1000000000000000037,"periods_count":4,"final_class":665},{"id":708,"name":"7А","info":null,"head_teacher":1134,"year":2017,"dnevnik_id":1000000000000000060,"periods_count":4,"final_class":665}],"marks":[{"mark":4.620689655172414,"terminal_mark":5,"student":10801,"class":685,"subject":532,"teacher":1141},{"mark":4.323529411764706,"terminal_mark":4,"student":10830,"class":685,"subject":532,"teacher":1141},{"mark":4.611111111111111,"terminal_mark":5,"student":10881,"class":685,"subject":532,"teacher":1141},{"mark":3.36,"terminal_mark":3,"student":10904,"class":685,"subject":532,"teacher":1141},{"mark":4.512195121951219,"terminal_mark":5,"student":10963,"class":685,"subject":532,"teacher":1141},{"mark":3.2333333333333334,"terminal_mark":3,"student":10969,"class":685,"subject":532,"teacher":1141},{"mark":2.9444444444444446,"terminal_mark":3,"student":10980,"class":685,"subject":532,"teacher":1141},{"mark":3.4827586206896552,"terminal_mark":4,"student":10986,"class":685,"subject":532,"teacher":1141},{"mark":4.6,"terminal_mark":5,"student":11005,"class":685,"subject":532,"teacher":1141},{"mark":3.6666666666666665,"terminal_mark":4,"student":11045,"class":685,"subject":532,"teacher":1141},{"mark":4.487804878048781,"terminal_mark":5,"student":11050,"class":685,"subject":532,"teacher":1141},{"mark":3.5714285714285716,"terminal_mark":4,"student":11068,"class":685,"subject":532,"teacher":1141},{"mark":4.5813953488372094,"terminal_mark":5,"student":11100,"class":685,"subject":532,"teacher":1141},{"mark":4.549019607843137,"terminal_mark":5,"student":11109,"class":685,"subject":532,"teacher":1141},{"mark":4.545454545454546,"terminal_mark":5,"student":11119,"class":685,"subject":532,"teacher":1141},{"mark":3.3125,"terminal_mark":3,"student":11167,"class":685,"subject":532,"teacher":1141},{"mark":4.666666666666667,"terminal_mark":5,"student":11169,"class":685,"subject":532,"teacher":1141},{"mark":4.8125,"terminal_mark":5,"student":11170,"class":685,"subject":532,"teacher":1141},{"mark":3.433333333333333,"terminal_mark":3,"student":11175,"class":685,"subject":532,"teacher":1141},{"mark":4.818181818181818,"terminal_mark":5,"student":11997,"class":685,"subject":532,"teacher":1141},{"mark":4.819672131147541,"terminal_mark":5,"student":10801,"class":685,"subject":524,"teacher":1088},{"mark":4.7846153846153845,"terminal_mark":5,"student":10830,"class":685,"subject":524,"teacher":1088},{"mark":4.7924528301886795,"terminal_mark":5,"student":10881,"class":685,"subject":524,"teacher":1088},{"mark":3.891891891891892,"terminal_mark":4,"student":10904,"class":685,"subject":524,"teacher":1088},{"mark":4.808219178082192,"terminal_mark":5,"student":10963,"class":685,"subject":524,"teacher":1088},{"mark":3.3035714285714284,"terminal_mark":3,"student":10969,"class":685,"subject":524,"teacher":1088},{"mark":4.75,"terminal_mark":5,"student":10980,"class":685,"subject":524,"teacher":1088},{"mark":4.802816901408451,"terminal_mark":5,"student":10986,"class":685,"subject":524,"teacher":1088},{"mark":4.666666666666667,"terminal_mark":5,"student":11005,"class":685,"subject":524,"teacher":1088},{"mark":4.8,"terminal_mark":5,"student":11045,"class":685,"subject":524,"teacher":1088},{"mark":4.828571428571428,"terminal_mark":5,"student":11050,"class":685,"subject":524,"teacher":1088},{"mark":4.142857142857143,"terminal_mark":5,"student":11068,"class":685,"subject":524,"teacher":1088},{"mark":4.655172413793103,"terminal_mark":5,"student":11100,"class":685,"subject":524,"teacher":1088},{"mark":4.388059701492537,"terminal_mark":4,"student":11109,"class":685,"subject":524,"teacher":1088},{"mark":4.92,"terminal_mark":5,"student":11119,"class":685,"subject":524,"teacher":1088},{"mark":4.630434782608695,"terminal_mark":5,"student":11167,"class":685,"subject":524,"teacher":1088},{"mark":4.8125,"terminal_mark":5,"student":11169,"class":685,"subject":524,"teacher":1088},{"mark":4.904761904761905,"terminal_mark":5,"student":11170,"class":685,"subject":524,"teacher":1088},{"mark":3.9107142857142856,"terminal_mark":4,"student":11175,"class":685,"subject":524,"teacher":1088},{"mark":4.944444444444445,"terminal_mark":5,"student":11997,"class":685,"subject":524,"teacher":1088},{"mark":4.782608695652174,"terminal_mark":5,"student":10801,"class":685,"subject":526,"teacher":1134},{"mark":4.633333333333334,"terminal_mark":5,"student":10830,"class":685,"subject":526,"teacher":1134},{"mark":4.7,"terminal_mark":5,"student":10881,"class":685,"subject":526,"teacher":1134},{"mark":4.166666666666667,"terminal_mark":4,"student":10904,"class":685,"subject":526,"teacher":1134},{"mark":4.756756756756757,"terminal_mark":5,"student":10963,"class":685,"subject":526,"teacher":1134},{"mark":3.7586206896551726,"terminal_mark":4,"student":10969,"class":685,"subject":526,"teacher":1134},{"mark":4.571428571428571,"terminal_mark":4,"student":10980,"class":685,"subject":526,"teacher":1134},{"mark":4.633333333333334,"terminal_mark":5,"student":10986,"class":685,"subject":526,"teacher":1134},{"mark":4.689655172413793,"terminal_mark":5,"student":11005,"class":685,"subject":526,"teacher":1134},{"mark":4.666666666666667,"terminal_mark":5,"student":11045,"class":685,"subject":526,"teacher":1134},{"mark":4.625,"terminal_mark":5,"student":11050,"class":685,"subject":526,"teacher":1134},{"mark":4.75,"terminal_mark":5,"student":11068,"class":685,"subject":526,"teacher":1134},{"mark":4.588235294117647,"terminal_mark":5,"student":11100,"class":685,"subject":526,"teacher":1134},{"mark":4.178571428571429,"terminal_mark":4,"student":11109,"class":685,"subject":526,"teacher":1134},{"mark":4.818181818181818,"terminal_mark":5,"student":11119,"class":685,"subject":526,"teacher":1134},{"mark":4.25,"terminal_mark":4,"student":11167,"class":685,"subject":526,"teacher":1134},{"mark":4.636363636363637,"terminal_mark":5,"student":11169,"class":685,"subject":526,"teacher":1134},{"mark":4.92,"terminal_mark":5,"student":11170,"class":685,"subject":526,"teacher":1134},{"mark":3.45,"terminal_mark":4,"student":11175,"class":685,"subject":526,"teacher":1134},{"mark":4.857142857142857,"terminal_mark":5,"student":11997,"class":685,"subject":526,"teacher":1134},{"mark":4.833333333333333,"terminal_mark":5,"student":10801,"class":685,"subject":527,"teacher":1136},{"mark":4.611111111111111,"terminal_mark":5,"student":10830,"class":685,"subject":527,"teacher":1136},{"mark":4.722222222222222,"terminal_mark":5,"student":10881,"class":685,"subject":527,"teacher":1136},{"mark":4.444444444444445,"terminal_mark":4,"student":10904,"class":685,"subject":527,"teacher":1136},{"mark":4.761904761904762,"terminal_mark":5,"student":10963,"class":685,"subject":527,"teacher":1136},{"mark":4.090909090909091,"terminal_mark":4,"student":10969,"class":685,"subject":527,"teacher":1136},{"mark":4.533333333333333,"terminal_mark":4,"student":10980,"class":685,"subject":527,"teacher":1136},{"mark":4.72,"terminal_mark":5,"student":10986,"class":685,"subject":527,"teacher":1136},{"mark":4.625,"terminal_mark":5,"student":11005,"class":685,"subject":527,"teacher":1136},{"mark":4.4,"terminal_mark":4,"student":11045,"class":685,"subject":527,"teacher":1136},{"mark":4.65,"terminal_mark":5,"student":11050,"class":685,"subject":527,"teacher":1136},{"mark":5.0,"terminal_mark":5,"student":11068,"class":685,"subject":527,"teacher":1136},{"mark":4.75,"terminal_mark":5,"student":11100,"class":685,"subject":527,"teacher":1136},{"mark":4.380952380952381,"terminal_mark":5,"student":11109,"class":685,"subject":527,"teacher":1136},{"mark":4.75,"terminal_mark":5,"student":11119,"class":685,"subject":527,"teacher":1136},{"mark":4.5625,"terminal_mark":4,"student":11167,"class":685,"subject":527,"teacher":1136},{"mark":4.7727272727272725,"terminal_mark":5,"student":11169,"class":685,"subject":527,"teacher":1136},{"mark":4.870967741935484,"terminal_mark":5,"student":11170,"class":685,"subject":527,"teacher":1136},{"mark":3.823529411764706,"terminal_mark":4,"student":11175,"class":685,"subject":527,"teacher":1136},{"mark":4.809523809523809,"terminal_mark":5,"student":11997,"class":685,"subject":527,"teacher":1136},{"mark":4.4375,"terminal_mark":4,"student":10801,"class":685,"subject":533,"teacher":1141},{"mark":4.052631578947368,"terminal_mark":4,"student":10830,"class":685,"subject":533,"teacher":1141},{"mark":4.461538461538462,"terminal_mark":5,"student":10881,"class":685,"subject":533,"teacher":1141},{"mark":3.230769230769231,"terminal_mark":3,"student":10904,"class":685,"subject":533,"teacher":1141},{"mark":4.421052631578948,"terminal_mark":5,"student":10963,"class":685,"subject":533,"teacher":1141},{"mark":3.1052631578947367,"terminal_mark":3,"student":10969,"class":685,"subject":533,"teacher":1141},{"mark":2.75,"terminal_mark":3,"student":10980,"class":685,"subject":533,"teacher":1141},{"mark":3.5,"terminal_mark":4,"student":10986,"class":685,"subject":533,"teacher":1141},{"mark":4.588235294117647,"terminal_mark":5,"student":11005,"class":685,"subject":533,"teacher":1141},{"mark":3.5714285714285716,"terminal_mark":4,"student":11045,"class":685,"subject":533,"teacher":1141},{"mark":4.411764705882353,"terminal_mark":5,"student":11050,"class":685,"subject":533,"teacher":1141},{"mark":3.6666666666666665,"terminal_mark":4,"student":11068,"class":685,"subject":533,"teacher":1141},{"mark":4.3,"terminal_mark":5,"student":11100,"class":685,"subject":533,"teacher":1141},{"mark":3.764705882352941,"terminal_mark":4,"student":11109,"class":685,"subject":533,"teacher":1141},{"mark":4.333333333333333,"terminal_mark":5,"student":11119,"class":685,"subject":533,"teacher":1141},{"mark":3.3333333333333335,"terminal_mark":3,"student":11167,"class":685,"subject":533,"teacher":1141},{"mark":4.722222222222222,"terminal_mark":5,"student":11169,"class":685,"subject":533,"teacher":1141},{"mark":5.0,"terminal_mark":5,"student":11170,"class":685,"subject":533,"teacher":1141},{"mark":3.0,"terminal_mark":3,"student":11175,"class":685,"subject":533,"teacher":1141},{"mark":4.833333333333333,"terminal_mark":5,"student":11997,"class":685,"subject":533,"teacher":1141},{"mark":5.0,"terminal_mark":5,"student":10801,"class":685,"subject":553,"teacher":1095},{"mark":5.0,"terminal_mark":5,"student":10830,"class":685,"subject":553,"teacher":1095},{"mark":5.0,"terminal_mark":5,"student":10881,"class":685,"subject":553,"teacher":1095},{"mark":5.0,"terminal_mark":5,"student":10904,"class":685,"subject":553,"teacher":1095},{"mark":5.0,"terminal_mark":5,"student":10963,"class":685,"subject":553,"teacher":1095},{"mark":5.0,"terminal_mark":5,"student":10969,"class":685,"subject":553,"teacher":1095},{"mark":5.0,"terminal_mark":5,"student":10980,"class":685,"subject":553,"teacher":1095},{"mark":5.0,"terminal_mark":5,"student":10986,"class":685,"subject":553,"teacher":1095},{"mark":5.0,"terminal_mark":5,"student":11005,"class":685,"subject":553,"teacher":1095},{"mark":5.0,"terminal_mark":5,"student":11045,"class":685,"subject":553,"teacher":1095},{"mark":5.0,"terminal_mark":5,"student":11050,"class":685,"subject":553,"teacher":1095},{"mark":5.0,"terminal_mark":5,"student":11068,"class":685,"subject":553,"teacher":1095},{"mark":5.0,"terminal_mark":5,"student":11100,"class":685,"subject":553,"teacher":1095},{"mark":5.0,"terminal_mark":5,"student":11109,"class":685,"subject":553,"teacher":1095},{"mark":5.0,"terminal_mark":5,"student":11119,"class":685,"subject":553,"teacher":1095},{"mark":5.0,"terminal_mark":5,"student":11167,"class":685,"subject":553,"teacher":1095},{"mark":5.0,"terminal_mark":5,"student":11169,"class":685,"subject":553,"teacher":1095},{"mark":5.0,"terminal_mark":5,"student":11170,"class":685,"subject":553,"teacher":1095},{"mark":5.0,"terminal_mark":5,"student":11175,"class":685,"subject":553,"teacher":1095},{"mark":5.0,"terminal_mark":5,"student":11997,"class":685,"subject":553,"teacher":1095},{"mark":4.88,"terminal_mark":5,"student":10801,"class":685,"subject":529,"teacher":1123},{"mark":4.291666666666667,"terminal_mark":4,"student":10830,"class":685,"subject":529,"teacher":1123},{"mark":4.7,"terminal_mark":5,"student":10881,"class":685,"subject":529,"teacher":1123},{"mark":4.277777777777778,"terminal_mark":4,"student":10904,"class":685,"subject":529,"teacher":1123},{"mark":4.942857142857143,"terminal_mark":5,"student":10963,"class":685,"subject":529,"teacher":1123},{"mark":4.285714285714286,"terminal_mark":4,"student":10969,"class":685,"subject":529,"teacher":1123},{"mark":4.2727272727272725,"terminal_mark":5,"student":10980,"class":685,"subject":529,"teacher":1123},{"mark":4.88,"terminal_mark":5,"student":10986,"class":685,"subject":529,"teacher":1123},{"mark":4.761904761904762,"terminal_mark":5,"student":11005,"class":685,"subject":529,"teacher":1123},{"mark":4.916666666666667,"terminal_mark":5,"student":11045,"class":685,"subject":529,"teacher":1123},{"mark":4.642857142857143,"terminal_mark":5,"student":11050,"class":685,"subject":529,"teacher":1123},{"mark":4.75,"terminal_mark":5,"student":11068,"class":685,"subject":529,"teacher":1123},{"mark":4.68,"terminal_mark":5,"student":11100,"class":685,"subject":529,"teacher":1123},{"mark":4.375,"terminal_mark":5,"student":11109,"class":685,"subject":529,"teacher":1123},{"mark":5.0,"terminal_mark":5,"student":11119,"class":685,"subject":529,"teacher":1123},{"mark":4.4375,"terminal_mark":4,"student":11167,"class":685,"subject":529,"teacher":1123},{"mark":4.809523809523809,"terminal_mark":5,"student":11169,"class":685,"subject":529,"teacher":1123},{"mark":4.928571428571429,"terminal_mark":5,"student":11170,"class":685,"subject":529,"teacher":1123},{"mark":4.185185185185185,"terminal_mark":4,"student":11175,"class":685,"subject":529,"teacher":1123},{"mark":4.964285714285714,"terminal_mark":5,"student":11997,"class":685,"subject":529,"teacher":1123},{"mark":5.0,"terminal_mark":5,"student":10801,"class":685,"subject":535,"teacher":1082},{"mark":4.7,"terminal_mark":5,"student":10830,"class":685,"subject":535,"teacher":1082},{"mark":5.0,"terminal_mark":5,"student":10881,"class":685,"subject":535,"teacher":1082},{"mark":4.625,"terminal_mark":5,"student":10904,"class":685,"subject":535,"teacher":1082},{"mark":5.0,"terminal_mark":5,"student":10963,"class":685,"subject":535,"teacher":1082},{"mark":4.625,"terminal_mark":5,"student":10969,"class":685,"subject":535,"teacher":1082},{"mark":4.8,"terminal_mark":5,"student":10980,"class":685,"subject":535,"teacher":1082},{"mark":4.75,"terminal_mark":5,"student":10986,"class":685,"subject":535,"teacher":1082},{"mark":5.0,"terminal_mark":5,"student":11005,"class":685,"subject":535,"teacher":1082},{"mark":5.0,"terminal_mark":5,"student":11045,"class":685,"subject":535,"teacher":1082},{"mark":4.75,"terminal_mark":5,"student":11050,"class":685,"subject":535,"teacher":1082},{"mark":5.0,"terminal_mark":5,"student":11068,"class":685,"subject":535,"teacher":1082},{"mark":4.9,"terminal_mark":5,"student":11100,"class":685,"subject":535,"teacher":1082},{"mark":5.0,"terminal_mark":5,"student":11109,"class":685,"subject":535,"teacher":1082},{"mark":5.0,"terminal_mark":5,"student":11119,"class":685,"subject":535,"teacher":1082},{"mark":4.625,"terminal_mark":5,"student":11167,"class":685,"subject":535,"teacher":1082},{"mark":4.888888888888889,"terminal_mark":5,"student":11169,"class":685,"subject":535,"teacher":1082},{"mark":4.916666666666667,"terminal_mark":5,"student":11170,"class":685,"subject":535,"teacher":1082},{"mark":4.75,"terminal_mark":5,"student":11175,"class":685,"subject":535,"teacher":1082},{"mark":4.9,"terminal_mark":5,"student":11997,"class":685,"subject":535,"teacher":1082},{"mark":5.0,"terminal_mark":5,"student":10801,"class":685,"subject":530,"teacher":1075},{"mark":4.5,"terminal_mark":5,"student":10830,"class":685,"subject":530,"teacher":1075},{"mark":4.923076923076923,"terminal_mark":5,"student":10881,"class":685,"subject":530,"teacher":1075},{"mark":4.7,"terminal_mark":5,"student":10904,"class":685,"subject":530,"teacher":1075},{"mark":4.933333333333334,"terminal_mark":5,"student":10963,"class":685,"subject":530,"teacher":1075},{"mark":4.6,"terminal_mark":5,"student":10969,"class":685,"subject":530,"teacher":1075},{"mark":4.75,"terminal_mark":5,"student":10980,"class":685,"subject":530,"teacher":1075},{"mark":4.933333333333334,"terminal_mark":5,"student":10986,"class":685,"subject":530,"teacher":1075},{"mark":5.0,"terminal_mark":5,"student":11005,"class":685,"subject":530,"teacher":1075},{"mark":5.0,"terminal_mark":5,"student":11045,"class":685,"subject":530,"teacher":1075},{"mark":4.888888888888889,"terminal_mark":5,"student":11050,"class":685,"subject":530,"teacher":1075},{"mark":4.666666666666667,"terminal_mark":5,"student":11068,"class":685,"subject":530,"teacher":1075},{"mark":4.833333333333333,"terminal_mark":5,"student":11100,"class":685,"subject":530,"teacher":1075},{"mark":4.857142857142857,"terminal_mark":5,"student":11109,"class":685,"subject":530,"teacher":1075},{"mark":5.0,"terminal_mark":5,"student":11119,"class":685,"subject":530,"teacher":1075},{"mark":4.666666666666667,"terminal_mark":4,"student":11167,"class":685,"subject":530,"teacher":1075},{"mark":5.0,"terminal_mark":5,"student":11169,"class":685,"subject":530,"teacher":1075},{"mark":4.909090909090909,"terminal_mark":5,"student":11170,"class":685,"subject":530,"teacher":1075},{"mark":4.428571428571429,"terminal_mark":4,"student":11175,"class":685,"subject":530,"teacher":1075},{"mark":5.0,"terminal_mark":5,"student":11997,"class":685,"subject":530,"teacher":1075},{"mark":4.809523809523809,"terminal_mark":5,"student":10801,"class":685,"subject":531,"teacher":1144},{"mark":4.333333333333333,"terminal_mark":4,"student":10830,"class":685,"subject":531,"teacher":1144},{"mark":4.7,"terminal_mark":5,"student":10881,"class":685,"subject":531,"teacher":1144},{"mark":3.8666666666666667,"terminal_mark":4,"student":10904,"class":685,"subject":531,"teacher":1144},{"mark":4.961538461538462,"terminal_mark":5,"student":10963,"class":685,"subject":531,"teacher":1144},{"mark":3.75,"terminal_mark":4,"student":10969,"class":685,"subject":531,"teacher":1144},{"mark":4.111111111111111,"terminal_mark":4,"student":10980,"class":685,"subject":531,"teacher":1144},{"mark":4.75,"terminal_mark":5,"student":10986,"class":685,"subject":531,"teacher":1144},{"mark":4.833333333333333,"terminal_mark":5,"student":11005,"class":685,"subject":531,"teacher":1144},{"mark":4.333333333333333,"terminal_mark":4,"student":11045,"class":685,"subject":531,"teacher":1144},{"mark":4.777777777777778,"terminal_mark":5,"student":11050,"class":685,"subject":531,"teacher":1144},{"mark":5.0,"terminal_mark":5,"student":11068,"class":685,"subject":531,"teacher":1144},{"mark":4.666666666666667,"terminal_mark":5,"student":11100,"class":685,"subject":531,"teacher":1144},{"mark":4.388888888888889,"terminal_mark":4,"student":11109,"class":685,"subject":531,"teacher":1144},{"mark":4.6,"terminal_mark":5,"student":11119,"class":685,"subject":531,"teacher":1144},{"mark":4.357142857142857,"terminal_mark":4,"student":11167,"class":685,"subject":531,"teacher":1144},{"mark":4.894736842105263,"terminal_mark":5,"student":11169,"class":685,"subject":531,"teacher":1144},{"mark":4.809523809523809,"terminal_mark":5,"student":11170,"class":685,"subject":531,"teacher":1144},{"mark":3.5555555555555554,"terminal_mark":4,"student":11175,"class":685,"subject":531,"teacher":1144},{"mark":4.88,"terminal_mark":5,"student":11997,"class":685,"subject":531,"teacher":1144},{"mark":4.583333333333333,"terminal_mark":5,"student":10801,"class":685,"subject":514,"teacher":1144},{"mark":3.9545454545454546,"terminal_mark":4,"student":10830,"class":685,"subject":514,"teacher":1144},{"mark":4.297872340425532,"terminal_mark":5,"student":10881,"class":685,"subject":514,"teacher":1144},{"mark":3.9047619047619047,"terminal_mark":4,"student":10904,"class":685,"subject":514,"teacher":1144},{"mark":4.574074074074074,"terminal_mark":5,"student":10963,"class":685,"subject":514,"teacher":1144},{"mark":3.3773584905660377,"terminal_mark":3,"student":10969,"class":685,"subject":514,"teacher":1144},{"mark":3.642857142857143,"terminal_mark":3,"student":10980,"class":685,"subject":514,"teacher":1144},{"mark":3.738095238095238,"terminal_mark":4,"student":10986,"class":685,"subject":514,"teacher":1144},{"mark":4.541666666666667,"terminal_mark":5,"student":11005,"class":685,"subject":514,"teacher":1144},{"mark":3.608695652173913,"terminal_mark":4,"student":11045,"class":685,"subject":514,"teacher":1144},{"mark":4.571428571428571,"terminal_mark":5,"student":11050,"class":685,"subject":514,"teacher":1144},{"mark":4.0,"terminal_mark":4,"student":11068,"class":685,"subject":514,"teacher":1144},{"mark":3.7954545454545454,"terminal_mark":4,"student":11100,"class":685,"subject":514,"teacher":1144},{"mark":3.5,"terminal_mark":3,"student":11109,"class":685,"subject":514,"teacher":1144},{"mark":4.576923076923077,"terminal_mark":5,"student":11119,"class":685,"subject":514,"teacher":1144},{"mark":3.772727272727273,"terminal_mark":4,"student":11167,"class":685,"subject":514,"teacher":1144},{"mark":4.721311475409836,"terminal_mark":5,"student":11169,"class":685,"subject":514,"teacher":1144},{"mark":4.704545454545454,"terminal_mark":5,"student":11170,"class":685,"subject":514,"teacher":1144},{"mark":3.0555555555555554,"terminal_mark":3,"student":11175,"class":685,"subject":514,"teacher":1144},{"mark":4.649122807017544,"terminal_mark":5,"student":11997,"class":685,"subject":514,"teacher":1144},{"mark":3.869565217391304,"terminal_mark":4,"student":10801,"class":685,"subject":534,"teacher":1080},{"mark":4.1923076923076925,"terminal_mark":5,"student":10830,"class":685,"subject":534,"teacher":1080},{"mark":4.592592592592593,"terminal_mark":5,"student":10881,"class":685,"subject":534,"teacher":1080},{"mark":3.1739130434782608,"terminal_mark":3,"student":10904,"class":685,"subject":534,"teacher":1080},{"mark":4.466666666666667,"terminal_mark":5,"student":10963,"class":685,"subject":534,"teacher":1080},{"mark":3.0,"terminal_mark":3,"student":10969,"class":685,"subject":534,"teacher":1080},{"mark":3.066666666666667,"terminal_mark":3,"student":10980,"class":685,"subject":534,"teacher":1080},{"mark":3.619047619047619,"terminal_mark":4,"student":10986,"class":685,"subject":534,"teacher":1080},{"mark":4.612903225806452,"terminal_mark":5,"student":11005,"class":685,"subject":534,"teacher":1080},{"mark":3.4,"terminal_mark":4,"student":11045,"class":685,"subject":534,"teacher":1080},{"mark":4.65625,"terminal_mark":5,"student":11050,"class":685,"subject":534,"teacher":1080},{"mark":3.8,"terminal_mark":4,"student":11068,"class":685,"subject":534,"teacher":1080},{"mark":4.666666666666667,"terminal_mark":5,"student":11100,"class":685,"subject":534,"teacher":1080},{"mark":3.84375,"terminal_mark":4,"student":11109,"class":685,"subject":534,"teacher":1080},{"mark":4.2,"terminal_mark":5,"student":11119,"class":685,"subject":534,"teacher":1080},{"mark":3.2142857142857144,"terminal_mark":3,"student":11167,"class":685,"subject":534,"teacher":1080},{"mark":4.647058823529412,"terminal_mark":5,"student":11169,"class":685,"subject":534,"teacher":1080},{"mark":4.78125,"terminal_mark":5,"student":11170,"class":685,"subject":534,"teacher":1080},{"mark":3.0,"terminal_mark":3,"student":11175,"class":685,"subject":534,"teacher":1080},{"mark":4.878048780487805,"terminal_mark":5,"student":11997,"class":685,"subject":534,"teacher":1080},{"mark":5.0,"terminal_mark":5,"student":10801,"class":685,"subject":515,"teacher":1111},{"mark":5.0,"terminal_mark":5,"student":10830,"class":685,"subject":515,"teacher":1111},{"mark":5.0,"terminal_mark":5,"student":10881,"class":685,"subject":515,"teacher":1111},{"mark":5.0,"terminal_mark":5,"student":10904,"class":685,"subject":515,"teacher":1111},{"mark":5.0,"terminal_mark":5,"student":10963,"class":685,"subject":515,"teacher":1111},{"mark":4.7272727272727275,"terminal_mark":5,"student":10969,"class":685,"subject":515,"teacher":1111},{"mark":5.0,"terminal_mark":5,"student":10980,"class":685,"subject":515,"teacher":1111},{"mark":5.0,"terminal_mark":5,"student":10986,"class":685,"subject":515,"teacher":1111},{"mark":5.0,"terminal_mark":5,"student":11005,"class":685,"subject":515,"teacher":1111},{"mark":5.0,"terminal_mark":5,"student":11045,"class":685,"subject":515,"teacher":1111},{"mark":5.0,"terminal_mark":5,"student":11050,"class":685,"subject":515,"teacher":1111},{"mark":5.0,"terminal_mark":5,"student":11068,"class":685,"subject":515,"teacher":1111},{"mark":5.0,"terminal_mark":5,"student":11100,"class":685,"subject":515,"teacher":1111},{"mark":4.75,"terminal_mark":5,"student":11109,"class":685,"subject":515,"teacher":1111},{"mark":5.0,"terminal_mark":5,"student":11119,"class":685,"subject":515,"teacher":1111},{"mark":5.0,"terminal_mark":5,"student":11167,"class":685,"subject":515,"teacher":1111},{"mark":5.0,"terminal_mark":5,"student":11169,"class":685,"subject":515,"teacher":1111},{"mark":5.0,"terminal_mark":5,"student":11170,"class":685,"subject":515,"teacher":1111},{"mark":4.714285714285714,"terminal_mark":5,"student":11175,"class":685,"subject":515,"teacher":1111},{"mark":4.9375,"terminal_mark":5,"student":11997,"class":685,"subject":515,"teacher":1111},{"mark":4.5,"terminal_mark":5,"student":10801,"class":685,"subject":536,"teacher":1081},{"mark":4.588235294117647,"terminal_mark":5,"student":10830,"class":685,"subject":536,"teacher":1081},{"mark":4.636363636363637,"terminal_mark":5,"student":10881,"class":685,"subject":536,"teacher":1081},{"mark":4.071428571428571,"terminal_mark":4,"student":10904,"class":685,"subject":536,"teacher":1081},{"mark":4.6,"terminal_mark":5,"student":10963,"class":685,"subject":536,"teacher":1081},{"mark":3.7058823529411766,"terminal_mark":4,"student":10969,"class":685,"subject":536,"teacher":1081},{"mark":3.25,"terminal_mark":3,"student":10980,"class":685,"subject":536,"teacher":1081},{"mark":4.411764705882353,"terminal_mark":4,"student":10986,"class":685,"subject":536,"teacher":1081},{"mark":4.695652173913044,"terminal_mark":5,"student":11005,"class":685,"subject":536,"teacher":1081},{"mark":4.0,"terminal_mark":4,"student":11045,"class":685,"subject":536,"teacher":1081},{"mark":4.714285714285714,"terminal_mark":5,"student":11050,"class":685,"subject":536,"teacher":1081},{"mark":4.0,"terminal_mark":5,"student":11068,"class":685,"subject":536,"teacher":1081},{"mark":4.6,"terminal_mark":5,"student":11100,"class":685,"subject":536,"teacher":1081},{"mark":3.869565217391304,"terminal_mark":4,"student":11109,"class":685,"subject":536,"teacher":1081},{"mark":4.846153846153846,"terminal_mark":5,"student":11119,"class":685,"subject":536,"teacher":1081},{"mark":3.8333333333333335,"terminal_mark":4,"student":11167,"class":685,"subject":536,"teacher":1081},{"mark":4.7894736842105265,"terminal_mark":5,"student":11169,"class":685,"subject":536,"teacher":1081},{"mark":4.833333333333333,"terminal_mark":5,"student":11170,"class":685,"subject":536,"teacher":1081},{"mark":3.2666666666666666,"terminal_mark":3,"student":11175,"class":685,"subject":536,"teacher":1081},{"mark":4.9,"terminal_mark":5,"student":11997,"class":685,"subject":536,"teacher":1081},{"mark":5.0,"terminal_mark":5,"student":10801,"class":685,"subject":516,"teacher":1075},{"mark":4.555555555555555,"terminal_mark":5,"student":10830,"class":685,"subject":516,"teacher":1075},{"mark":5.0,"terminal_mark":5,"student":10881,"class":685,"subject":516,"teacher":1075},{"mark":4.875,"terminal_mark":5,"student":10904,"class":685,"subject":516,"teacher":1075},{"mark":5.0,"terminal_mark":5,"student":10963,"class":685,"subject":516,"teacher":1075},{"mark":4.666666666666667,"terminal_mark":5,"student":10969,"class":685,"subject":516,"teacher":1075},{"mark":4.833333333333333,"terminal_mark":5,"student":10980,"class":685,"subject":516,"teacher":1075},{"mark":4.916666666666667,"terminal_mark":5,"student":10986,"class":685,"subject":516,"teacher":1075},{"mark":5.0,"terminal_mark":5,"student":11005,"class":685,"subject":516,"teacher":1075},{"mark":5.0,"terminal_mark":5,"student":11045,"class":685,"subject":516,"teacher":1075},{"mark":4.777777777777778,"terminal_mark":5,"student":11050,"class":685,"subject":516,"teacher":1075},{"mark":4.75,"terminal_mark":5,"student":11068,"class":685,"subject":516,"teacher":1075},{"mark":4.875,"terminal_mark":5,"student":11100,"class":685,"subject":516,"teacher":1075},{"mark":4.7,"terminal_mark":5,"student":11109,"class":685,"subject":516,"teacher":1075},{"mark":5.0,"terminal_mark":5,"student":11119,"class":685,"subject":516,"teacher":1075},{"mark":4.777777777777778,"terminal_mark":4,"student":11167,"class":685,"subject":516,"teacher":1075},{"mark":4.9,"terminal_mark":5,"student":11169,"class":685,"subject":516,"teacher":1075},{"mark":5.0,"terminal_mark":5,"student":11170,"class":685,"subject":516,"teacher":1075},{"mark":4.6,"terminal_mark":4,"student":11175,"class":685,"subject":516,"teacher":1075},{"mark":5.0,"terminal_mark":5,"student":11997,"class":685,"subject":516,"teacher":1075},{"mark":4.916666666666667,"terminal_mark":5,"student":10801,"class":685,"subject":554,"teacher":1169},{"mark":4.818181818181818,"terminal_mark":5,"student":10830,"class":685,"subject":554,"teacher":1169},{"mark":4.888888888888889,"terminal_mark":5,"student":10881,"class":685,"subject":554,"teacher":1169},{"mark":4.266666666666667,"terminal_mark":4,"student":10904,"class":685,"subject":554,"teacher":1169},{"mark":4.923076923076923,"terminal_mark":5,"student":10963,"class":685,"subject":554,"teacher":1169},{"mark":3.5652173913043477,"terminal_mark":4,"student":10969,"class":685,"subject":554,"teacher":1169},{"mark":5.0,"terminal_mark":5,"student":10980,"class":685,"subject":554,"teacher":1169},{"mark":4.826086956521739,"terminal_mark":5,"student":10986,"class":685,"subject":554,"teacher":1169},{"mark":4.851851851851852,"terminal_mark":5,"student":11005,"class":685,"subject":554,"teacher":1169},{"mark":5.0,"terminal_mark":5,"student":11045,"class":685,"subject":554,"teacher":1169},{"mark":4.75,"terminal_mark":5,"student":11050,"class":685,"subject":554,"teacher":1169},{"mark":5.0,"terminal_mark":null,"student":11068,"class":685,"subject":554,"teacher":1169},{"mark":4.777777777777778,"terminal_mark":5,"student":11100,"class":685,"subject":554,"teacher":1169},{"mark":4.961538461538462,"terminal_mark":5,"student":11109,"class":685,"subject":554,"teacher":1169},{"mark":5.0,"terminal_mark":5,"student":11119,"class":685,"subject":554,"teacher":1169},{"mark":4.703703703703703,"terminal_mark":5,"student":11167,"class":685,"subject":554,"teacher":1169},{"mark":4.8076923076923075,"terminal_mark":5,"student":11169,"class":685,"subject":554,"teacher":1169},{"mark":4.961538461538462,"terminal_mark":5,"student":11170,"class":685,"subject":554,"teacher":1169},{"mark":3.9130434782608696,"terminal_mark":4,"student":11175,"class":685,"subject":554,"teacher":1169},{"mark":5.0,"terminal_mark":5,"student":11997,"class":685,"subject":554,"teacher":1169},{"mark":4.5,"terminal_mark":null,"student":10801,"class":685,"subject":517,"teacher":1141},{"mark":4.0,"terminal_mark":null,"student":10830,"class":685,"subject":517,"teacher":1141},{"mark":5.0,"terminal_mark":null,"student":10881,"class":685,"subject":517,"teacher":1141},{"mark":null,"terminal_mark":null,"student":10904,"class":685,"subject":517,"teacher":1141},{"mark":4.666666666666667,"terminal_mark":null,"student":11109,"class":685,"subject":517,"teacher":1141},{"mark":5.0,"terminal_mark":null,"student":11170,"class":685,"subject":517,"teacher":1141},{"mark":4.666666666666667,"terminal_mark":null,"student":11997,"class":685,"subject":517,"teacher":1141},{"mark":5.0,"terminal_mark":5,"student":10801,"class":685,"subject":518,"teacher":1097},{"mark":5.0,"terminal_mark":5,"student":10830,"class":685,"subject":518,"teacher":1097},{"mark":5.0,"terminal_mark":5,"student":10881,"class":685,"subject":518,"teacher":1097},{"mark":4.777777777777778,"terminal_mark":5,"student":10904,"class":685,"subject":518,"teacher":1097},{"mark":5.0,"terminal_mark":5,"student":10963,"class":685,"subject":518,"teacher":1097},{"mark":4.8,"terminal_mark":5,"student":10969,"class":685,"subject":518,"teacher":1097},{"mark":5.0,"terminal_mark":5,"student":10980,"class":685,"subject":518,"teacher":1097},{"mark":5.0,"terminal_mark":5,"student":10986,"class":685,"subject":518,"teacher":1097},{"mark":5.0,"terminal_mark":5,"student":11005,"class":685,"subject":518,"teacher":1097},{"mark":5.0,"terminal_mark":5,"student":11045,"class":685,"subject":518,"teacher":1097},{"mark":5.0,"terminal_mark":5,"student":11050,"class":685,"subject":518,"teacher":1097},{"mark":5.0,"terminal_mark":null,"student":11068,"class":685,"subject":518,"teacher":1097},{"mark":4.909090909090909,"terminal_mark":5,"student":11100,"class":685,"subject":518,"teacher":1097},{"mark":5.0,"terminal_mark":5,"student":11109,"class":685,"subject":518,"teacher":1097},{"mark":5.0,"terminal_mark":5,"student":11119,"class":685,"subject":518,"teacher":1097},{"mark":4.9,"terminal_mark":5,"student":11167,"class":685,"subject":518,"teacher":1097},{"mark":5.0,"terminal_mark":5,"student":11169,"class":685,"subject":518,"teacher":1097},{"mark":4.9,"terminal_mark":5,"student":11170,"class":685,"subject":518,"teacher":1097},{"mark":5.0,"terminal_mark":5,"student":11175,"class":685,"subject":518,"teacher":1097},{"mark":5.0,"terminal_mark":5,"student":11997,"class":685,"subject":518,"teacher":1097},{"mark":null,"terminal_mark":null,"student":10801,"class":685,"subject":555,"teacher":1141},{"mark":null,"terminal_mark":null,"student":10830,"class":685,"subject":555,"teacher":1141},{"mark":null,"terminal_mark":null,"student":10881,"class":685,"subject":555,"teacher":1141},{"mark":null,"terminal_mark":null,"student":10904,"class":685,"subject":555,"teacher":1141},{"mark":5.0,"terminal_mark":null,"student":11170,"class":685,"subject":555,"teacher":1141},{"mark":null,"terminal_mark":null,"student":11997,"class":685,"subject":555,"teacher":1141},{"mark":5.0,"terminal_mark":null,"student":11109,"class":685,"subject":556,"teacher":1169},{"mark":5.0,"terminal_mark":null,"student":11170,"class":685,"subject":557,"teacher":1080},{"mark":5.0,"terminal_mark":5,"student":10801,"class":685,"subject":522,"teacher":1117},{"mark":5.0,"terminal_mark":5,"student":10830,"class":685,"subject":522,"teacher":1117},{"mark":5.0,"terminal_mark":5,"student":10881,"class":685,"subject":522,"teacher":1117},{"mark":4.833333333333333,"terminal_mark":5,"student":10904,"class":685,"subject":522,"teacher":1117},{"mark":5.0,"terminal_mark":5,"student":10963,"class":685,"subject":522,"teacher":1117},{"mark":4.181818181818182,"terminal_mark":4,"student":10969,"class":685,"subject":522,"teacher":1117},{"mark":4.833333333333333,"terminal_mark":5,"student":10980,"class":685,"subject":522,"teacher":1117},{"mark":4.954545454545454,"terminal_mark":5,"student":10986,"class":685,"subject":522,"teacher":1117},{"mark":5.0,"terminal_mark":5,"student":11005,"class":685,"subject":522,"teacher":1117},{"mark":5.0,"terminal_mark":5,"student":11045,"class":685,"subject":522,"teacher":1117},{"mark":5.0,"terminal_mark":5,"student":11050,"class":685,"subject":522,"teacher":1117},{"mark":5.0,"terminal_mark":null,"student":11068,"class":685,"subject":522,"teacher":1117},{"mark":4.956521739130435,"terminal_mark":5,"student":11100,"class":685,"subject":522,"teacher":1117},{"mark":5.0,"terminal_mark":5,"student":11109,"class":685,"subject":522,"teacher":1117},{"mark":5.0,"terminal_mark":5,"student":11119,"class":685,"subject":522,"teacher":1117},{"mark":4.954545454545454,"terminal_mark":5,"student":11167,"class":685,"subject":522,"teacher":1117},{"mark":5.0,"terminal_mark":5,"student":11169,"class":685,"subject":522,"teacher":1117},{"mark":5.0,"terminal_mark":5,"student":11170,"class":685,"subject":522,"teacher":1117},{"mark":4.52,"terminal_mark":5,"student":11175,"class":685,"subject":522,"teacher":1117},{"mark":5.0,"terminal_mark":5,"student":11997,"class":685,"subject":522,"teacher":1117},{"mark":5.0,"terminal_mark":null,"student":11045,"class":685,"subject":558,"teacher":1088},{"mark":5.0,"terminal_mark":null,"student":11175,"class":685,"subject":558,"teacher":1088},{"mark":null,"terminal_mark":null,"student":10801,"class":685,"subject":559,"teacher":1123},{"mark":null,"terminal_mark":null,"student":10881,"class":685,"subject":559,"teacher":1123},{"mark":null,"terminal_mark":null,"student":10904,"class":685,"subject":559,"teacher":1123},{"mark":null,"terminal_mark":null,"student":10969,"class":685,"subject":559,"teacher":1123},{"mark":null,"terminal_mark":null,"student":11050,"class":685,"subject":559,"teacher":1123},{"mark":null,"terminal_mark":null,"student":11167,"class":685,"subject":559,"teacher":1123},{"mark":null,"terminal_mark":null,"student":11175,"class":685,"subject":559,"teacher":1123}],"subjects":[{"id":514,"name":"Рус. язык","type":"Русский язык и литература","dnevnik_id":3000000000000001},{"id":515,"name":"Физкультура","type":"Неизвестно","dnevnik_id":3000000000000002},{"id":516,"name":"Кубановедение","type":"Прочее","dnevnik_id":3000000000000003},{"id":517,"name":"Математика","type":"Математика","dnevnik_id":3000000000000004},{"id":518,"name":"Шахматы","type":"Прочее","dnevnik_id":3000000000000005},{"id":522,"name":"Технология","type":"Технология","dnevnik_id":3000000000000009},{"id":524,"name":"Англ. язык","type":"Иностранный язык","dnevnik_id":3000000000000011},{"id":526,"name":"Биология","type":"Естествознание","dnevnik_id":3000000000000013},{"id":527,"name":"География","type":"Социальные науки","dnevnik_id":3000000000000014},{"id":529,"name":"История","type":"Социальные науки","dnevnik_id":3000000000000016},{"id":530,"name":"Обществознание","type":"Социальные науки","dnevnik_id":3000000000000017},{"id":531,"name":"Литература","type":"Русский язык и литература","dnevnik_id":3000000000000018},{"id":532,"name":"Алгебра","type":"Математика","dnevnik_id":3000000000000019},{"id":533,"name":"Геометрия","type":"Математика","dnevnik_id":3000000000000020},{"id":534,"name":"Физика","type":"Естествознание","dnevnik_id":3000000000000021},{"id":535,"name":"ОБЖ","type":"Физическая культура","dnevnik_id":3000000000000022},{"id":536,"name":"Химия","type":"Естествознание","dnevnik_id":3000000000000023},{"id":553,"name":"Искусство","type":"Искусство","dnevnik_id":3000000000000040},{"id":554,"name":"ИКТ","type":"Технология","dnevnik_id":3000000000000041},{"id":555,"name":"Математика (Э)","type":"Элективы","dnevnik_id":3000000000000042},{"id":556,"name":"Информатика (Э)","type":"Элективы","dnevnik_id":3000000000000043},{"id":557,"name":"Физика (Э)","type":"Элективы","dnevnik_id":3000000000000044},{"id":558,"name":"Англ.яз (Э)","type":"Элективы","dnevnik_id":3000000000000045},{"id":559,"name":"История (Э)","type":"Элективы","dnevnik_id":3000000000000046}],"teachers":[{"id":1075,"full_name":"Вакуленко Артём Филимонович","birthday":"1980-05-27","tel":null,"email":null,"dnevnik_id":1000000000013,"dnevnik_person_id":1000000000013,"job":"Учитель"},{"id":1080,"full_name":"Максимова Инесса Владленовна","birthday":"1992-08-24","tel":null,"email":null,"dnevnik_id":1000000000018,"dnevnik_person_id":1000000000018,"job":"Учитель, Редактор"},{"id":1081,"full_name":"Софроньева Фатима Ефремовна","birthday":"2008-07-18","tel":"+7-(972)-957-36-48","email":"ireland1888@live.com","dnevnik_id":1000000000019,"dnevnik_person_id":1000000000019,"job":"Учитель, Редактор"},{"id":1082,"full_name":"Вильмонт Магистриан Ермолаевич","birthday":"1992-01-25","tel":null,"email":null,"dnevnik_id":1000000000020,"dnevnik_person_id":1000000000020,"job":"Учитель, Редактор"},{"id":1088,"full_name":"Клепова Антонина Венедиктовна","birthday":"1993-05-04","tel":null,"email":null,"dnevnik_id":1000000000026,"dnevnik_person_id":1000000000026,"job":"Учитель"},{"id":1095,"full_name":"Корнильева Ава Артуровна","birthday":"2009-01-05","tel":"+7-(968)-642-29-47","email":null,"dnevnik_id":1000000000032,"dnevnik_person_id":1000000000033,"job":"Учитель"},{"id":1097,"full_name":"Безрученко Никита Герасимович","birthday":"2009-01-21","tel":null,"email":null,"dnevnik_id":1000000000034,"dnevnik_person_id":1000000000035,"job":"Учитель, Редактор"},{"id":1111,"full_name":"Язов Афанасий Устинович","birthday":"2009-10-08","tel":null,"email":null,"dnevnik_id":1000000000046,"dnevnik_person_id":1000000000049,"job":"Учитель, Редактор"},{"id":1117,"full_name":"Хаустов Афанасий Ануфриевич","birthday":"2009-03-14","tel":null,"email":null,"dnevnik_id":1000000000052,"dnevnik_person_id":1000000000055,"job":"Учитель"},{"id":1123,"full_name":"Степная Октябрина Борисовна","birthday":"1989-03-12","tel":"+7-(962)-243-94-53","email":null,"dnevnik_id":1000000000058,"dnevnik_person_id":1000000000061,"job":"Учитель, Редактор"},{"id":1134,"full_name":"Козлачкова Виола Тихоновна","birthday":"1987-08-19","tel":null,"email":null,"dnevnik_id":1000000000068,"dnevnik_person_id":1000000000072,"job":"Учитель, Редактор"},{"id":1136,"full_name":"Сальников Аникита Жанович","birthday":"1992-10-09","tel":null,"email":null,"dnevnik_id":1000000000069,"dnevnik_person_id":1000000000074,"job":"Учитель, Редактор"},{"id":1141,"full_name":"Бодрова Лиана Богдановна","birthday":"2009-07-20","tel":null,"email":null,"dnevnik_id":1000000000073,"dnevnik_person_id":1000000000079,"job":"Учитель, Редактор, Родитель"},{"id":1144,"full_name":"Кошелева Цагана Аароновна","birthday":"1987-05-14","tel":null,"email":null,"dnevnik_id":1000000000075,"dnevnik_person_id":1000000000082,"job":"Учитель, Редактор"},{"id":1169,"full_name":"Аствацатурова Римма Филатовна","birthday":null,"tel":null,"email":null,"dnevnik_id":1000000000099,"dnevnik_person_id":null,"job":null}]}