{"id":11561,"full_name":"Аверкиева Елена Трофимовна","birthday":"2000-12-15","tel":"+7-(968)-848-31-59","email":null,"dnevnik_id":1000000000474,"dnevnik_person_id":1000000000866,"info":null,"entered":"2014-09-01","leaved":"2018-07-31","parents":null,"class":{"id":719,"name":"11Б","info":"физико-математический","head_teacher":null,"year":2017,"dnevnik_id":1000000000000000071,"periods_count":2,"final_class":null},"previous_classes":[],"marks":{"marks":[{"id":570839,"mark":null,"student":11561,"lesson_info":{"id":11342,"subject":532,"teacher":1122,"class":719},"presence":1,"period":215,"date":"2017-09-02"},{"id":570840,"mark":null,"student":11561,"lesson_info":{"id":11342,"subject":532,"teacher":1122,"class":719},"presence":1,"period":215,"date":"2017-09-02"},{"id":570841,"mark":4,"student":11561,"lesson_info":{"id":11342,"subject":532,"teacher":1122,"class":719},"presence":0,"period":215,"date":"2017-09-04"},{"id":570842,"mark":4,"student":11561,"lesson_info":{"id":11342,"subject":532,"teacher":1122,"class":719},"presence":0,"period":215,"date":"2017-09-09"},{"id":570843,"mark":4,"student":11561,"lesson_info":{"id":11342,"subject":532,"teacher":1122,"class":719},"presence":0,"period":215,"date":"2017-09-11"},{"id":570844,"mark":5,"student":11561,"lesson_info":{"id":11342,"subject":532,"teacher":1122,"class":719},"presence":0,"period":215,"date":"2017-09-18"},{"id":570845,"mark":4,"student":11561,"lesson_info":{"id":11342,"subject":532,"teacher":1122,"class":719},"presence":0,"period":215,"date":"2017-09-23"},{"id":570846,"mark":4,"student":11561,"lesson_info":{"id":11342,"subject":532,"teacher":1122,"class":719},"presence":0,"period":215,"date":"2017-09-23"},{"id":570847,"mark":3,"student":11561,"lesson_info":{"id":11342,"subject":532,"teacher":1122,"class":719},"presence":0,"period":215,"date":"2017-09-25"},{"id":570848,"mark":4,"student":11561,"lesson_info":{"id":11342,"subject":532,"teacher":1122,"class":719},"presence":0,"period":215,"date":"2017-09-25"},{"id":570849,"mark":null,"student":11561,"lesson_info":{"id":11342,"subject":532,"teacher":1122,"class":719},"presence":1,"period":215,"date":"2017-09-30"},{"id":570850,"mark":null,"student":11561,"lesson_info":{"id":11342,"subject":532,"teacher":1122,"class":719},"presence":1,"period":215,"date":"2017-09-30"},{"id":570851,"mark":5,"student":11561,"lesson_info":{"id":11342,"subject":532,"teacher":1122,"class":719},"presence":0,"period":215,"date":"2017-10-02"},{"id":570852,"mark":4,"student":11561,"lesson_info":{"id":11342,"subject":532,"teacher":1122,"class":719},"presence":0,"period":215,"date":"2017-10-02"},{"id":570853,"mark":3,"student":11561,"lesson_info":{"id":11342,"subject":532,"teacher":1122,"class":719},"presence":0,"period":215,"date":"2017-10-07"},{"id":570854,"mark":5,"student":11561,"lesson_info":{"id":11342,"subject":532,"teacher":1122,"class":719},"presence":0,"period":215,"date":"2017-10-09"},{"id":570855,"mark":null,"student":11561,"lesson_info":{"id":11342,"subject":532,"teacher":1122,"class":719},"presence":1,"period":215,"date":"2017-10-14"},{"id":570856,"mark":null,"student":11561,"lesson_info":{"id":11342,"subject":532,"teacher":1122,"class":719},"presence":1,"period":215,"date":"2017-10-14"},{"id":570857,"mark":4,"student":11561,"lesson_info":{"id":11342,"subject":532,"teacher":1122,"class":719},"presence":0,"period":215,"date":"2017-10-16"},{"id":570858,"mark":3,"student":11561,"lesson_info":{"id":11342,"subject":532,"teacher":1122,"class":719},"presence":0,"period":215,"date":"2017-10-16"},{"id":570859,"mark":null,"student":11561,"lesson_info":{"id":11342,"subject":532,"teacher":1122,"class":719},"presence":1,"period":215,"date":"2017-10-21"},{"id":570860,"mark":null,"student":11561,"lesson_info":{"id":11342,"subject":532,"teacher":1122,"class":719},"presence":1,"period":215,"date":"2017-10-21"},{"id":570861,"mark":4,"student":11561,"lesson_info":{"id":11342,"subject":532,"teacher":1122,"class":719},"presence":0,"period":215,"date":"2017-10-23"},{"id":570862,"mark":4,"student":11561,"lesson_info":{"id":11342,"subject":532,"teacher":1122,"class":719},"presence":0,"period":215,"date":"2017-11-10"},{"id":570863,"mark":4,"student":11561,"lesson_info":{"id":11342,"subject":532,"teacher":1122,"class":719},"presence":0,"period":215,"date":"2017-11-13"},{"id":570864,"mark":4,"student":11561,"lesson_info":{"id":11342,"subject":532,"teacher":1122,"class":719},"presence":0,"period":215,"date":"2017-11-17"},{"id":570865,"mark":4,"student":11561,"lesson_info":{"id":11342,"subject":532,"teacher":1122,"class":719},"presence":0,"period":215,"date":"2017-11-20"},{"id":570866,"mark":4,"student":11561,"lesson_info":{"id":11342,"subject":532,"teacher":1122,"class":719},"presence":0,"period":215,"date":"2017-11-20"},{"id":570867,"mark":5,"student":11561,"lesson_info":{"id":11342,"subject":532,"teacher":1122,"class":719},"presence":0,"period":215,"date":"2017-11-24"},{"id":570868,"mark":4,"student":11561,"lesson_info":{"id":11342,"subject":532,"teacher":1122,"class":719},"presence":0,"period":215,"date":"2017-11-27"},{"id":570869,"mark":4,"student":11561,"lesson_info":{"id":11342,"subject":532,"teacher":1122,"class":719},"presence":0,"period":215,"date":"2017-12-01"},{"id":570870,"mark":4,"student":11561,"lesson_info":{"id":11342,"subject":532,"teacher":1122,"class":719},"presence":0,"period":215,"date":"2017-12-04"},{"id":570871,"mark":5,"student":11561,"lesson_info":{"id":11342,"subject":532,"teacher":1122,"class":719},"presence":0,"period":215,"date":"2017-12-08"},{"id":570872,"mark":5,"student":11561,"lesson_info":{"id":11342,"subject":532,"teacher":1122,"class":719},"presence":0,"period":215,"date":"2017-12-08"},{"id":570873,"mark":2,"student":11561,"lesson_info":{"id":11342,"subject":532,"teacher":1122,"class":719},"presence":0,"period":215,"date":"2017-12-11"},{"id":570874,"mark":5,"student":11561,"lesson_info":{"id":11342,"subject":532,"teacher":1122,"class":719},"presence":0,"period":215,"date":"2017-12-15"},{"id":570875,"mark":4,"student":11561,"lesson_info":{"id":11342,"subject":532,"teacher":1122,"class":719},"presence":0,"period":215,"date":"2017-12-18"},{"id":570876,"mark":4,"student":11561,"lesson_info":{"id":11342,"subject":532,"teacher":1122,"class":719},"presence":0,"period":215,"date":"2017-12-18"},{"id":570877,"mark":4,"student":11561,"lesson_info":{"id":11342,"subject":532,"teacher":1122,"class":719},"presence":0,"period":215,"date":"2017-12-22"},{"id":571417,"mark":3,"student":11561,"lesson_info":{"id":11343,"subject":524,"teacher":1153,"class":719},"presence":0,"period":215,"date":"2017-09-06"},{"id":571418,"mark":4,"student":11561,"lesson_info":{"id":11343,"subject":524,"teacher":1153,"class":719},"presence":0,"period":215,"date":"2017-09-15"},{"id":571419,"mark":4,"student":11561,"lesson_info":{"id":11343,"subject":524,"teacher":1153,"class":719},"presence":0,"period":215,"date":"2017-09-27"},{"id":571420,"mark":3,"student":11561,"lesson_info":{"id":11343,"subject":524,"teacher":1153,"class":719},"presence":0,"period":215,"date":"2017-10-11"},{"id":571421,"mark":null,"student":11561,"lesson_info":{"id":11343,"subject":524,"teacher":1153,"class":719},"presence":1,"period":215,"date":"2017-10-18"},{"id":571422,"mark":null,"student":11561,"lesson_info":{"id":11343,"subject":524,"teacher":1153,"class":719},"presence":1,"period":215,"date":"2017-10-18"},{"id":571423,"mark":4,"student":11561,"lesson_info":{"id":11343,"subject":524,"teacher":1153,"class":719},"presence":0,"period":215,"date":"2017-10-25"},{"id":571424,"mark":4,"student":11561,"lesson_info":{"id":11343,"subject":524,"teacher":1153,"class":719},"presence":0,"period":215,"date":"2017-10-27"},{"id":571425,"mark":4,"student":11561,"lesson_info":{"id":11343,"subject":524,"teacher":1153,"class":719},"presence":0,"period":215,"date":"2017-11-08"},{"id":571426,"mark":4,"student":11561,"lesson_info":{"id":11343,"subject":524,"teacher":1153,"class":719},"presence":0,"period":215,"date":"2017-11-17"},{"id":571427,"mark":4,"student":11561,"lesson_info":{"id":11343,"subject":524,"teacher":1153,"class":719},"presence":0,"period":215,"date":"2017-11-22"},{"id":571428,"mark":4,"student":11561,"lesson_info":{"id":11343,"subject":524,"teacher":1153,"class":719},"presence":0,"period":215,"date":"2017-11-29"},{"id":571429,"mark":4,"student":11561,"lesson_info":{"id":11343,"subject":524,"teacher":1153,"class":719},"presence":0,"period":215,"date":"2017-12-01"},{"id":571430,"mark":4,"student":11561,"lesson_info":{"id":11343,"subject":524,"teacher":1153,"class":719},"presence":0,"period":215,"date":"2017-12-06"},{"id":571431,"mark":4,"student":11561,"lesson_info":{"id":11343,"subject":524,"teacher":1153,"class":719},"presence":0,"period":215,"date":"2017-12-13"},{"id":571432,"mark":4,"student":11561,"lesson_info":{"id":11343,"subject":524,"teacher":1153,"class":719},"presence":0,"period":215,"date":"2017-12-20"},{"id":571643,"mark":5,"student":11561,"lesson_info":{"id":11344,"subject":526,"teacher":1134,"class":719},"presence":0,"period":215,"date":"2017-09-13"},{"id":571644,"mark":4,"student":11561,"lesson_info":{"id":11344,"subject":526,"teacher":1134,"class":719},"presence":0,"period":215,"date":"2017-10-11"},{"id":571645,"mark":5,"student":11561,"lesson_info":{"id":11344,"subject":526,"teacher":1134,"class":719},"presence":0,"period":215,"date":"2017-10-20"},{"id":571646,"mark":4,"student":11561,"lesson_info":{"id":11344,"subject":526,"teacher":1134,"class":719},"presence":0,"period":215,"date":"2017-11-07"},{"id":571647,"mark":5,"student":11561,"lesson_info":{"id":11344,"subject":526,"teacher":1134,"class":719},"presence":0,"period":215,"date":"2017-11-21"},{"id":571648,"mark":5,"student":11561,"lesson_info":{"id":11344,"subject":526,"teacher":1134,"class":719},"presence":0,"period":215,"date":"2017-12-19"},{"id":571788,"mark":5,"student":11561,"lesson_info":{"id":11345,"subject":527,"teacher":1136,"class":719},"presence":0,"period":215,"date":"2017-09-08"},{"id":571789,"mark":5,"student":11561,"lesson_info":{"id":11345,"subject":527,"teacher":1136,"class":719},"presence":0,"period":215,"date":"2017-09-22"},{"id":571790,"mark":5,"student":11561,"lesson_info":{"id":11345,"subject":527,"teacher":1136,"class":719},"presence":0,"period":215,"date":"2017-10-06"},{"id":571791,"mark":5,"student":11561,"lesson_info":{"id":11345,"subject":527,"teacher":1136,"class":719},"presence":0,"period":215,"date":"2017-11-13"},{"id":571792,"mark":5,"student":11561,"lesson_info":{"id":11345,"subject":527,"teacher":1136,"class":719},"presence":0,"period":215,"date":"2017-11-27"},{"id":571793,"mark":4,"student":11561,"lesson_info":{"id":11345,"subject":527,"teacher":1136,"class":719},"presence":0,"period":215,"date":"2017-11-27"},{"id":571794,"mark":null,"student":11561,"lesson_info":{"id":11345,"subject":527,"teacher":1136,"class":719},"presence":1,"period":215,"date":"2017-12-11"},{"id":571795,"mark":null,"student":11561,"lesson_info":{"id":11345,"subject":527,"teacher":1136,"class":719},"presence":1,"period":215,"date":"2017-12-11"},{"id":572053,"mark":4,"student":11561,"lesson_info":{"id":11346,"subject":533,"teacher":1122,"class":719},"presence":0,"period":215,"date":"2017-09-15"},{"id":572054,"mark":4,"student":11561,"lesson_info":{"id":11346,"subject":533,"teacher":1122,"class":719},"presence":0,"period":215,"date":"2017-09-22"},{"id":572055,"mark":4,"student":11561,"lesson_info":{"id":11346,"subject":533,"teacher":1122,"class":719},"presence":0,"period":215,"date":"2017-09-29"},{"id":572056,"mark":4,"student":11561,"lesson_info":{"id":11346,"subject":533,"teacher":1122,"class":719},"presence":0,"period":215,"date":"2017-09-29"},{"id":572057,"mark":4,"student":11561,"lesson_info":{"id":11346,"subject":533,"teacher":1122,"class":719},"presence":0,"period":215,"date":"2017-10-06"},{"id":572058,"mark":null,"student":11561,"lesson_info":{"id":11346,"subject":533,"teacher":1122,"class":719},"presence":1,"period":215,"date":"2017-10-13"},{"id":572059,"mark":null,"student":11561,"lesson_info":{"id":11346,"subject":533,"teacher":1122,"class":719},"presence":1,"period":215,"date":"2017-10-13"},{"id":572060,"mark":4,"student":11561,"lesson_info":{"id":11346,"subject":533,"teacher":1122,"class":719},"presence":0,"period":215,"date":"2017-10-17"},{"id":572061,"mark":5,"student":11561,"lesson_info":{"id":11346,"subject":533,"teacher":1122,"class":719},"presence":0,"period":215,"date":"2017-10-17"},{"id":572062,"mark":4,"student":11561,"lesson_info":{"id":11346,"subject":533,"teacher":1122,"class":719},"presence":0,"period":215,"date":"2017-10-24"},{"id":572063,"mark":3,"student":11561,"lesson_info":{"id":11346,"subject":533,"teacher":1122,"class":719},"presence":0,"period":215,"date":"2017-11-08"},{"id":572064,"mark":4,"student":11561,"lesson_info":{"id":11346,"subject":533,"teacher":1122,"class":719},"presence":0,"period":215,"date":"2017-11-15"},{"id":572065,"mark":3,"student":11561,"lesson_info":{"id":11346,"subject":533,"teacher":1122,"class":719},"presence":0,"period":215,"date":"2017-11-22"},{"id":572066,"mark":4,"student":11561,"lesson_info":{"id":11346,"subject":533,"teacher":1122,"class":719},"presence":0,"period":215,"date":"2017-11-29"},{"id":572067,"mark":4,"student":11561,"lesson_info":{"id":11346,"subject":533,"teacher":1122,"class":719},"presence":0,"period":215,"date":"2017-12-06"},{"id":572068,"mark":4,"student":11561,"lesson_info":{"id":11346,"subject":533,"teacher":1122,"class":719},"presence":0,"period":215,"date":"2017-12-13"},{"id":572069,"mark":3,"student":11561,"lesson_info":{"id":11346,"subject":533,"teacher":1122,"class":719},"presence":0,"period":215,"date":"2017-12-20"},{"id":572344,"mark":5,"student":11561,"lesson_info":{"id":11347,"subject":528,"teacher":1115,"class":719},"presence":0,"period":215,"date":"2017-10-10"},{"id":572345,"mark":5,"student":11561,"lesson_info":{"id":11347,"subject":528,"teacher":1115,"class":719},"presence":0,"period":215,"date":"2017-11-14"},{"id":572346,"mark":4,"student":11561,"lesson_info":{"id":11347,"subject":528,"teacher":1115,"class":719},"presence":0,"period":215,"date":"2017-11-28"},{"id":572347,"mark":5,"student":11561,"lesson_info":{"id":11347,"subject":528,"teacher":1115,"class":719},"presence":0,"period":215,"date":"2017-12-12"},{"id":572348,"mark":5,"student":11561,"lesson_info":{"id":11347,"subject":528,"teacher":1115,"class":719},"presence":0,"period":215,"date":"2017-12-26"},{"id":572514,"mark":5,"student":11561,"lesson_info":{"id":11348,"subject":529,"teacher":1065,"class":719},"presence":0,"period":215,"date":"2017-09-21"},{"id":572515,"mark":4,"student":11561,"lesson_info":{"id":11348,"subject":529,"teacher":1065,"class":719},"presence":0,"period":215,"date":"2017-10-05"},{"id":572516,"mark":null,"student":11561,"lesson_info":{"id":11348,"subject":529,"teacher":1065,"class":719},"presence":1,"period":215,"date":"2017-10-12"},{"id":572517,"mark":null,"student":11561,"lesson_info":{"id":11348,"subject":529,"teacher":1065,"class":719},"presence":1,"period":215,"date":"2017-10-12"},{"id":572518,"mark":4,"student":11561,"lesson_info":{"id":11348,"subject":529,"teacher":1065,"class":719},"presence":0,"period":215,"date":"2017-11-14"},{"id":572519,"mark":null,"student":11561,"lesson_info":{"id":11348,"subject":529,"teacher":1065,"class":719},"presence":1,"period":215,"date":"2017-11-21"},{"id":572520,"mark":4,"student":11561,"lesson_info":{"id":11348,"subject":529,"teacher":1065,"class":719},"presence":0,"period":215,"date":"2017-11-28"},{"id":572521,"mark":null,"student":11561,"lesson_info":{"id":11348,"subject":529,"teacher":1065,"class":719},"presence":1,"period":215,"date":"2017-12-12"},{"id":572522,"mark":null,"student":11561,"lesson_info":{"id":11348,"subject":529,"teacher":1065,"class":719},"presence":1,"period":215,"date":"2017-12-12"},{"id":572523,"mark":4,"student":11561,"lesson_info":{"id":11348,"subject":529,"teacher":1065,"class":719},"presence":0,"period":215,"date":"2017-12-19"},{"id":572735,"mark":null,"student":11561,"lesson_info":{"id":11349,"subject":535,"teacher":1082,"class":719},"presence":1,"period":215,"date":"2017-09-02"},{"id":572736,"mark":null,"student":11561,"lesson_info":{"id":11349,"subject":535,"teacher":1082,"class":719},"presence":1,"period":215,"date":"2017-09-02"},{"id":572737,"mark":4,"student":11561,"lesson_info":{"id":11349,"subject":535,"teacher":1082,"class":719},"presence":0,"period":215,"date":"2017-09-16"},{"id":572738,"mark":5,"student":11561,"lesson_info":{"id":11349,"subject":535,"teacher":1082,"class":719},"presence":0,"period":215,"date":"2017-09-30"},{"id":572739,"mark":5,"student":11561,"lesson_info":{"id":11349,"subject":535,"teacher":1082,"class":719},"presence":0,"period":215,"date":"2017-09-30"},{"id":572740,"mark":null,"student":11561,"lesson_info":{"id":11349,"subject":535,"teacher":1082,"class":719},"presence":1,"period":215,"date":"2017-10-14"},{"id":572741,"mark":null,"student":11561,"lesson_info":{"id":11349,"subject":535,"teacher":1082,"class":719},"presence":1,"period":215,"date":"2017-10-14"},{"id":572742,"mark":5,"student":11561,"lesson_info":{"id":11349,"subject":535,"teacher":1082,"class":719},"presence":0,"period":215,"date":"2017-10-26"},{"id":572743,"mark":5,"student":11561,"lesson_info":{"id":11349,"subject":535,"teacher":1082,"class":719},"presence":0,"period":215,"date":"2017-11-25"},{"id":572744,"mark":5,"student":11561,"lesson_info":{"id":11349,"subject":535,"teacher":1082,"class":719},"presence":0,"period":215,"date":"2017-12-23"},{"id":572899,"mark":5,"student":11561,"lesson_info":{"id":11350,"subject":530,"teacher":1065,"class":719},"presence":0,"period":215,"date":"2017-09-20"},{"id":572900,"mark":5,"student":11561,"lesson_info":{"id":11350,"subject":530,"teacher":1065,"class":719},"presence":0,"period":215,"date":"2017-09-20"},{"id":572901,"mark":5,"student":11561,"lesson_info":{"id":11350,"subject":530,"teacher":1065,"class":719},"presence":0,"period":215,"date":"2017-10-11"},{"id":572902,"mark":4,"student":11561,"lesson_info":{"id":11350,"subject":530,"teacher":1065,"class":719},"presence":0,"period":215,"date":"2017-10-25"},{"id":572903,"mark":5,"student":11561,"lesson_info":{"id":11350,"subject":530,"teacher":1065,"class":719},"presence":0,"period":215,"date":"2017-10-25"},{"id":572904,"mark":5,"student":11561,"lesson_info":{"id":11350,"subject":530,"teacher":1065,"class":719},"presence":0,"period":215,"date":"2017-11-22"},{"id":572905,"mark":4,"student":11561,"lesson_info":{"id":11350,"subject":530,"teacher":1065,"class":719},"presence":0,"period":215,"date":"2017-12-06"},{"id":572906,"mark":4,"student":11561,"lesson_info":{"id":11350,"subject":530,"teacher":1065,"class":719},"presence":0,"period":215,"date":"2017-12-13"},{"id":572907,"mark":4,"student":11561,"lesson_info":{"id":11350,"subject":530,"teacher":1065,"class":719},"presence":0,"period":215,"date":"2017-12-20"},{"id":572908,"mark":4,"student":11561,"lesson_info":{"id":11350,"subject":530,"teacher":1065,"class":719},"presence":0,"period":215,"date":"2017-12-20"},{"id":573094,"mark":5,"student":11561,"lesson_info":{"id":11352,"subject":531,"teacher":1068,"class":719},"presence":0,"period":215,"date":"2017-09-07"},{"id":573095,"mark":5,"student":11561,"lesson_info":{"id":11352,"subject":531,"teacher":1068,"class":719},"presence":0,"period":215,"date":"2017-09-08"},{"id":573096,"mark":5,"student":11561,"lesson_info":{"id":11352,"subject":531,"teacher":1068,"class":719},"presence":0,"period":215,"date":"2017-09-21"},{"id":573097,"mark":4,"student":11561,"lesson_info":{"id":11352,"subject":531,"teacher":1068,"class":719},"presence":0,"period":215,"date":"2017-09-21"},{"id":573098,"mark":5,"student":11561,"lesson_info":{"id":11352,"subject":531,"teacher":1068,"class":719},"presence":0,"period":215,"date":"2017-09-28"},{"id":573099,"mark":4,"student":11561,"lesson_info":{"id":11352,"subject":531,"teacher":1068,"class":719},"presence":0,"period":215,"date":"2017-10-05"},{"id":573100,"mark":5,"student":11561,"lesson_info":{"id":11352,"subject":531,"teacher":1068,"class":719},"presence":0,"period":215,"date":"2017-10-06"},{"id":573101,"mark":null,"student":11561,"lesson_info":{"id":11352,"subject":531,"teacher":1068,"class":719},"presence":1,"period":215,"date":"2017-10-12"},{"id":573102,"mark":null,"student":11561,"lesson_info":{"id":11352,"subject":531,"teacher":1068,"class":719},"presence":1,"period":215,"date":"2017-10-12"},{"id":573103,"mark":4,"student":11561,"lesson_info":{"id":11352,"subject":531,"teacher":1068,"class":719},"presence":0,"period":215,"date":"2017-10-20"},{"id":573104,"mark":4,"student":11561,"lesson_info":{"id":11352,"subject":531,"teacher":1068,"class":719},"presence":0,"period":215,"date":"2017-10-24"},{"id":573105,"mark":5,"student":11561,"lesson_info":{"id":11352,"subject":531,"teacher":1068,"class":719},"presence":0,"period":215,"date":"2017-10-27"},{"id":573106,"mark":5,"student":11561,"lesson_info":{"id":11352,"subject":531,"teacher":1068,"class":719},"presence":0,"period":215,"date":"2017-11-07"},{"id":573107,"mark":4,"student":11561,"lesson_info":{"id":11352,"subject":531,"teacher":1068,"class":719},"presence":0,"period":215,"date":"2017-11-07"},{"id":573108,"mark":5,"student":11561,"lesson_info":{"id":11352,"subject":531,"teacher":1068,"class":719},"presence":0,"period":215,"date":"2017-11-16"},{"id":573109,"mark":5,"student":11561,"lesson_info":{"id":11352,"subject":531,"teacher":1068,"class":719},"presence":0,"period":215,"date":"2017-11-16"},{"id":573110,"mark":5,"student":11561,"lesson_info":{"id":11352,"subject":531,"teacher":1068,"class":719},"presence":0,"period":215,"date":"2017-11-21"},{"id":573111,"mark":5,"student":11561,"lesson_info":{"id":11352,"subject":531,"teacher":1068,"class":719},"presence":0,"period":215,"date":"2017-11-30"},{"id":573112,"mark":5,"student":11561,"lesson_info":{"id":11352,"subject":531,"teacher":1068,"class":719},"presence":0,"period":215,"date":"2017-12-05"},{"id":573113,"mark":5,"student":11561,"lesson_info":{"id":11352,"subject":531,"teacher":1068,"class":719},"presence":0,"period":215,"date":"2017-12-09"},{"id":573114,"mark":4,"student":11561,"lesson_info":{"id":11352,"subject":531,"teacher":1068,"class":719},"presence":0,"period":215,"date":"2017-12-14"},{"id":573115,"mark":5,"student":11561,"lesson_info":{"id":11352,"subject":531,"teacher":1068,"class":719},"presence":0,"period":215,"date":"2017-12-19"},{"id":573116,"mark":5,"student":11561,"lesson_info":{"id":11352,"subject":531,"teacher":1068,"class":719},"presence":0,"period":215,"date":"2017-12-23"},{"id":573387,"mark":4,"student":11561,"lesson_info":{"id":11353,"subject":514,"teacher":1068,"class":719},"presence":0,"period":215,"date":"2017-09-12"},{"id":573388,"mark":4,"student":11561,"lesson_info":{"id":11353,"subject":514,"teacher":1068,"class":719},"presence":0,"period":215,"date":"2017-09-12"},{"id":573389,"mark":5,"student":11561,"lesson_info":{"id":11353,"subject":514,"teacher":1068,"class":719},"presence":0,"period":215,"date":"2017-09-19"},{"id":573390,"mark":5,"student":11561,"lesson_info":{"id":11353,"subject":514,"teacher":1068,"class":719},"presence":0,"period":215,"date":"2017-09-19"},{"id":573391,"mark":5,"student":11561,"lesson_info":{"id":11353,"subject":514,"teacher":1068,"class":719},"presence":0,"period":215,"date":"2017-09-26"},{"id":573392,"mark":4,"student":11561,"lesson_info":{"id":11353,"subject":514,"teacher":1068,"class":719},"presence":0,"period":215,"date":"2017-09-26"},{"id":573393,"mark":5,"student":11561,"lesson_info":{"id":11353,"subject":514,"teacher":1068,"class":719},"presence":0,"period":215,"date":"2017-10-03"},{"id":573394,"mark":4,"student":11561,"lesson_info":{"id":11353,"subject":514,"teacher":1068,"class":719},"presence":0,"period":215,"date":"2017-10-10"},{"id":573395,"mark":4,"student":11561,"lesson_info":{"id":11353,"subject":514,"teacher":1068,"class":719},"presence":0,"period":215,"date":"2017-10-19"},{"id":573396,"mark":4,"student":11561,"lesson_info":{"id":11353,"subject":514,"teacher":1068,"class":719},"presence":0,"period":215,"date":"2017-10-26"},{"id":573397,"mark":5,"student":11561,"lesson_info":{"id":11353,"subject":514,"teacher":1068,"class":719},"presence":0,"period":215,"date":"2017-11-10"},{"id":573398,"mark":5,"student":11561,"lesson_info":{"id":11353,"subject":514,"teacher":1068,"class":719},"presence":0,"period":215,"date":"2017-11-17"},{"id":573399,"mark":4,"student":11561,"lesson_info":{"id":11353,"subject":514,"teacher":1068,"class":719},"presence":0,"period":215,"date":"2017-11-24"},{"id":573400,"mark":4,"student":11561,"lesson_info":{"id":11353,"subject":514,"teacher":1068,"class":719},"presence":0,"period":215,"date":"2017-12-01"},{"id":573401,"mark":4,"student":11561,"lesson_info":{"id":11353,"subject":514,"teacher":1068,"class":719},"presence":0,"period":215,"date":"2017-12-08"},{"id":573402,"mark":3,"student":11561,"lesson_info":{"id":11353,"subject":514,"teacher":1068,"class":719},"presence":0,"period":215,"date":"2017-12-15"},{"id":573403,"mark":4,"student":11561,"lesson_info":{"id":11353,"subject":514,"teacher":1068,"class":719},"presence":0,"period":215,"date":"2017-12-22"},{"id":573812,"mark":null,"student":11561,"lesson_info":{"id":11354,"subject":534,"teacher":1080,"class":719},"presence":1,"period":215,"date":"2017-09-02"},{"id":573813,"mark":null,"student":11561,"lesson_info":{"id":11354,"subject":534,"teacher":1080,"class":719},"presence":1,"period":215,"date":"2017-09-02"},{"id":573814,"mark":null,"student":11561,"lesson_info":{"id":11354,"subject":534,"teacher":1080,"class":719},"presence":1,"period":215,"date":"2017-09-05"},{"id":573815,"mark":null,"student":11561,"lesson_info":{"id":11354,"subject":534,"teacher":1080,"class":719},"presence":1,"period":215,"date":"2017-09-05"},{"id":573816,"mark":3,"student":11561,"lesson_info":{"id":11354,"subject":534,"teacher":1080,"class":719},"presence":0,"period":215,"date":"2017-09-12"},{"id":573817,"mark":2,"student":11561,"lesson_info":{"id":11354,"subject":534,"teacher":1080,"class":719},"presence":0,"period":215,"date":"2017-09-16"},{"id":573818,"mark":4,"student":11561,"lesson_info":{"id":11354,"subject":534,"teacher":1080,"class":719},"presence":0,"period":215,"date":"2017-09-25"},{"id":573819,"mark":4,"student":11561,"lesson_info":{"id":11354,"subject":534,"teacher":1080,"class":719},"presence":0,"period":215,"date":"2017-09-25"},{"id":573820,"mark":5,"student":11561,"lesson_info":{"id":11354,"subject":534,"teacher":1080,"class":719},"presence":0,"period":215,"date":"2017-09-30"},{"id":573821,"mark":3,"student":11561,"lesson_info":{"id":11354,"subject":534,"teacher":1080,"class":719},"presence":0,"period":215,"date":"2017-10-02"},{"id":573822,"mark":5,"student":11561,"lesson_info":{"id":11354,"subject":534,"teacher":1080,"class":719},"presence":0,"period":215,"date":"2017-10-02"},{"id":573823,"mark":3,"student":11561,"lesson_info":{"id":11354,"subject":534,"teacher":1080,"class":719},"presence":0,"period":215,"date":"2017-10-03"},{"id":573824,"mark":5,"student":11561,"lesson_info":{"id":11354,"subject":534,"teacher":1080,"class":719},"presence":0,"period":215,"date":"2017-10-10"},{"id":573825,"mark":null,"student":11561,"lesson_info":{"id":11354,"subject":534,"teacher":1080,"class":719},"presence":1,"period":215,"date":"2017-10-14"},{"id":573826,"mark":null,"student":11561,"lesson_info":{"id":11354,"subject":534,"teacher":1080,"class":719},"presence":1,"period":215,"date":"2017-10-14"},{"id":573827,"mark":3,"student":11561,"lesson_info":{"id":11354,"subject":534,"teacher":1080,"class":719},"presence":0,"period":215,"date":"2017-10-23"},{"id":573828,"mark":4,"student":11561,"lesson_info":{"id":11354,"subject":534,"teacher":1080,"class":719},"presence":0,"period":215,"date":"2017-11-14"},{"id":573829,"mark":4,"student":11561,"lesson_info":{"id":11354,"subject":534,"teacher":1080,"class":719},"presence":0,"period":215,"date":"2017-11-16"},{"id":573830,"mark":2,"student":11561,"lesson_info":{"id":11354,"subject":534,"teacher":1080,"class":719},"presence":0,"period":215,"date":"2017-11-28"},{"id":573831,"mark":3,"student":11561,"lesson_info":{"id":11354,"subject":534,"teacher":1080,"class":719},"presence":0,"period":215,"date":"2017-12-06"},{"id":573832,"mark":5,"student":11561,"lesson_info":{"id":11354,"subject":534,"teacher":1080,"class":719},"presence":0,"period":215,"date":"2017-12-12"},{"id":573833,"mark":3,"student":11561,"lesson_info":{"id":11354,"subject":534,"teacher":1080,"class":719},"presence":0,"period":215,"date":"2017-12-13"},{"id":573834,"mark":4,"student":11561,"lesson_info":{"id":11354,"subject":534,"teacher":1080,"class":719},"presence":0,"period":215,"date":"2017-12-21"},{"id":573835,"mark":4,"student":11561,"lesson_info":{"id":11354,"subject":534,"teacher":1080,"class":719},"presence":0,"period":215,"date":"2017-12-21"},{"id":573836,"mark":4,"student":11561,"lesson_info":{"id":11354,"subject":534,"teacher":1080,"class":719},"presence":0,"period":215,"date":"2017-12-27"},{"id":574353,"mark":null,"student":11561,"lesson_info":{"id":11355,"subject":515,"teacher":1102,"class":719},"presence":1,"period":215,"date":"2017-09-14"},{"id":574354,"mark":null,"student":11561,"lesson_info":{"id":11355,"subject":515,"teacher":1102,"class":719},"presence":1,"period":215,"date":"2017-09-14"},{"id":574355,"mark":null,"student":11561,"lesson_info":{"id":11355,"subject":515,"teacher":1102,"class":719},"presence":1,"period":215,"date":"2017-09-21"},{"id":574356,"mark":null,"student":11561,"lesson_info":{"id":11355,"subject":515,"teacher":1102,"class":719},"presence":1,"period":215,"date":"2017-09-21"},{"id":574357,"mark":5,"student":11561,"lesson_info":{"id":11355,"subject":515,"teacher":1102,"class":719},"presence":0,"period":215,"date":"2017-09-28"},{"id":574358,"mark":5,"student":11561,"lesson_info":{"id":11355,"subject":515,"teacher":1102,"class":719},"presence":0,"period":215,"date":"2017-10-05"},{"id":574359,"mark":5,"student":11561,"lesson_info":{"id":11355,"subject":515,"teacher":1102,"class":719},"presence":0,"period":215,"date":"2017-10-05"},{"id":574360,"mark":null,"student":11561,"lesson_info":{"id":11355,"subject":515,"teacher":1102,"class":719},"presence":1,"period":215,"date":"2017-10-12"},{"id":574361,"mark":null,"student":11561,"lesson_info":{"id":11355,"subject":515,"teacher":1102,"class":719},"presence":1,"period":215,"date":"2017-10-12"},{"id":574362,"mark":4,"student":11561,"lesson_info":{"id":11355,"subject":515,"teacher":1102,"class":719},"presence":0,"period":215,"date":"2017-10-19"},{"id":574363,"mark":4,"student":11561,"lesson_info":{"id":11355,"subject":515,"teacher":1102,"class":719},"presence":0,"period":215,"date":"2017-10-19"},{"id":574364,"mark":5,"student":11561,"lesson_info":{"id":11355,"subject":515,"teacher":1102,"class":719},"presence":0,"period":215,"date":"2017-10-26"},{"id":574365,"mark":5,"student":11561,"lesson_info":{"id":11355,"subject":515,"teacher":1102,"class":719},"presence":0,"period":215,"date":"2017-10-26"},{"id":574366,"mark":null,"student":11561,"lesson_info":{"id":11355,"subject":515,"teacher":1102,"class":719},"presence":1,"period":215,"date":"2017-11-23"},{"id":574367,"mark":null,"student":11561,"lesson_info":{"id":11355,"subject":515,"teacher":1102,"class":719},"presence":1,"period":215,"date":"2017-11-23"},{"id":574368,"mark":null,"student":11561,"lesson_info":{"id":11355,"subject":515,"teacher":1102,"class":719},"presence":1,"period":215,"date":"2017-11-30"},{"id":574369,"mark":null,"student":11561,"lesson_info":{"id":11355,"subject":515,"teacher":1102,"class":719},"presence":1,"period":215,"date":"2017-11-30"},{"id":574370,"mark":5,"student":11561,"lesson_info":{"id":11355,"subject":515,"teacher":1102,"class":719},"presence":0,"period":215,"date":"2017-12-14"},{"id":574619,"mark":null,"student":11561,"lesson_info":{"id":11356,"subject":536,"teacher":1081,"class":719},"presence":1,"period":215,"date":"2017-09-26"},{"id":574620,"mark":null,"student":11561,"lesson_info":{"id":11356,"subject":536,"teacher":1081,"class":719},"presence":1,"period":215,"date":"2017-09-26"},{"id":574621,"mark":5,"student":11561,"lesson_info":{"id":11356,"subject":536,"teacher":1081,"class":719},"presence":0,"period":215,"date":"2017-10-10"},{"id":574622,"mark":5,"student":11561,"lesson_info":{"id":11356,"subject":536,"teacher":1081,"class":719},"presence":0,"period":215,"date":"2017-11-11"},{"id":574623,"mark":5,"student":11561,"lesson_info":{"id":11356,"subject":536,"teacher":1081,"class":719},"presence":0,"period":215,"date":"2017-11-25"},{"id":574747,"mark":4,"student":11561,"lesson_info":{"id":11357,"subject":516,"teacher":1065,"class":719},"presence":0,"period":215,"date":"2017-09-20"},{"id":574748,"mark":5,"student":11561,"lesson_info":{"id":11357,"subject":516,"teacher":1065,"class":719},"presence":0,"period":215,"date":"2017-10-04"},{"id":574749,"mark":5,"student":11561,"lesson_info":{"id":11357,"subject":516,"teacher":1065,"class":719},"presence":0,"period":215,"date":"2017-11-09"},{"id":574750,"mark":5,"student":11561,"lesson_info":{"id":11357,"subject":516,"teacher":1065,"class":719},"presence":0,"period":215,"date":"2017-12-07"},{"id":574751,"mark":null,"student":11561,"lesson_info":{"id":11357,"subject":516,"teacher":1065,"class":719},"presence":1,"period":215,"date":"2017-12-21"},{"id":574752,"mark":5,"student":11561,"lesson_info":{"id":11357,"subject":516,"teacher":1065,"class":719},"presence":0,"period":215,"date":"2017-12-21"},{"id":574940,"mark":5,"student":11561,"lesson_info":{"id":11358,"subject":554,"teacher":1115,"class":719},"presence":0,"period":215,"date":"2017-09-11"},{"id":574941,"mark":4,"student":11561,"lesson_info":{"id":11358,"subject":554,"teacher":1115,"class":719},"presence":0,"period":215,"date":"2017-09-18"},{"id":574942,"mark":5,"student":11561,"lesson_info":{"id":11358,"subject":554,"teacher":1115,"class":719},"presence":0,"period":215,"date":"2017-09-25"},{"id":574943,"mark":4,"student":11561,"lesson_info":{"id":11358,"subject":554,"teacher":1115,"class":719},"presence":0,"period":215,"date":"2017-10-02"},{"id":574944,"mark":5,"student":11561,"lesson_info":{"id":11358,"subject":554,"teacher":1115,"class":719},"presence":0,"period":215,"date":"2017-10-09"},{"id":574945,"mark":5,"student":11561,"lesson_info":{"id":11358,"subject":554,"teacher":1115,"class":719},"presence":0,"period":215,"date":"2017-10-17"},{"id":574946,"mark":5,"student":11561,"lesson_info":{"id":11358,"subject":554,"teacher":1115,"class":719},"presence":0,"period":215,"date":"2017-11-15"},{"id":574947,"mark":5,"student":11561,"lesson_info":{"id":11358,"subject":554,"teacher":1115,"class":719},"presence":0,"period":215,"date":"2017-12-06"},{"id":574948,"mark":5,"student":11561,"lesson_info":{"id":11358,"subject":554,"teacher":1115,"class":719},"presence":0,"period":215,"date":"2017-12-13"},{"id":575133,"mark":4,"student":11561,"lesson_info":{"id":11359,"subject":518,"teacher":1097,"class":719},"presence":0,"period":215,"date":"2017-09-23"},{"id":575134,"mark":5,"student":11561,"lesson_info":{"id":11359,"subject":518,"teacher":1097,"class":719},"presence":0,"period":215,"date":"2017-10-07"},{"id":575135,"mark":5,"student":11561,"lesson_info":{"id":11359,"subject":518,"teacher":1097,"class":719},"presence":0,"period":215,"date":"2017-10-17"},{"id":575136,"mark":4,"student":11561,"lesson_info":{"id":11359,"subject":518,"teacher":1097,"class":719},"presence":0,"period":215,"date":"2017-11-18"},{"id":575137,"mark":5,"student":11561,"lesson_info":{"id":11359,"subject":518,"teacher":1097,"class":719},"presence":0,"period":215,"date":"2017-12-02"},{"id":575138,"mark":5,"student":11561,"lesson_info":{"id":11359,"subject":518,"teacher":1097,"class":719},"presence":0,"period":215,"date":"2017-12-02"},{"id":575139,"mark":5,"student":11561,"lesson_info":{"id":11359,"subject":518,"teacher":1097,"class":719},"presence":0,"period":215,"date":"2017-12-16"},{"id":575227,"mark":null,"student":11561,"lesson_info":{"id":11360,"subject":555,"teacher":1122,"class":719},"presence":1,"period":215,"date":"2017-10-13"},{"id":575228,"mark":null,"student":11561,"lesson_info":{"id":11360,"subject":555,"teacher":1122,"class":719},"presence":1,"period":215,"date":"2017-10-13"},{"id":575289,"mark":5,"student":11561,"lesson_info":{"id":11362,"subject":567,"teacher":1179,"class":719},"presence":0,"period":215,"date":"2017-09-08"},{"id":575290,"mark":5,"student":11561,"lesson_info":{"id":11362,"subject":567,"teacher":1179,"class":719},"presence":0,"period":215,"date":"2017-10-16"},{"id":575291,"mark":5,"student":11561,"lesson_info":{"id":11362,"subject":567,"teacher":1179,"class":719},"presence":0,"period":215,"date":"2017-11-20"},{"id":847013,"mark":3,"student":11561,"lesson_info":{"id":11342,"subject":532,"teacher":1122,"class":719},"presence":0,"period":216,"date":"2018-01-12"},{"id":847014,"mark":5,"student":11561,"lesson_info":{"id":11342,"subject":532,"teacher":1122,"class":719},"presence":0,"period":216,"date":"2018-01-12"},{"id":847015,"mark":4,"student":11561,"lesson_info":{"id":11342,"subject":532,"teacher":1122,"class":719},"presence":0,"period":216,"date":"2018-01-15"},{"id":847016,"mark":4,"student":11561,"lesson_info":{"id":11342,"subject":532,"teacher":1122,"class":719},"presence":0,"period":216,"date":"2018-01-19"},{"id":847017,"mark":3,"student":11561,"lesson_info":{"id":11342,"subject":532,"teacher":1122,"class":719},"presence":0,"period":216,"date":"2018-01-22"},{"id":847018,"mark":4,"student":11561,"lesson_info":{"id":11342,"subject":532,"teacher":1122,"class":719},"presence":0,"period":216,"date":"2018-01-26"},{"id":847019,"mark":5,"student":11561,"lesson_info":{"id":11342,"subject":532,"teacher":1122,"class":719},"presence":0,"period":216,"date":"2018-01-29"},{"id":847020,"mark":4,"student":11561,"lesson_info":{"id":11342,"subject":532,"teacher":1122,"class":719},"presence":0,"period":216,"date":"2018-02-03"},{"id":847021,"mark":4,"student":11561,"lesson_info":{"id":11342,"subject":532,"teacher":1122,"class":719},"presence":0,"period":216,"date":"2018-02-10"},{"id":847022,"mark":5,"student":11561,"lesson_info":{"id":11342,"subject":532,"teacher":1122,"class":719},"presence":0,"period":216,"date":"2018-02-12"},{"id":847023,"mark":4,"student":11561,"lesson_info":{"id":11342,"subject":532,"teacher":1122,"class":719},"presence":0,"period":216,"date":"2018-02-17"},{"id":847024,"mark":5,"student":11561,"lesson_info":{"id":11342,"subject":532,"teacher":1122,"class":719},"presence":0,"period":216,"date":"2018-02-19"},{"id":847025,"mark":null,"student":11561,"lesson_info":{"id":11342,"subject":532,"teacher":1122,"class":719},"presence":1,"period":216,"date":"2018-02-26"},{"id":847026,"mark":null,"student":11561,"lesson_info":{"id":11342,"subject":532,"teacher":1122,"class":719},"presence":1,"period":216,"date":"2018-02-26"},{"id":847027,"mark":4,"student":11561,"lesson_info":{"id":11342,"subject":532,"teacher":1122,"class":719},"presence":0,"period":216,"date":"2018-03-03"},{"id":847028,"mark":5,"student":11561,"lesson_info":{"id":11342,"subject":532,"teacher":1122,"class":719},"presence":0,"period":216,"date":"2018-03-03"},{"id":847029,"mark":4,"student":11561,"lesson_info":{"id":11342,"subject":532,"teacher":1122,"class":719},"presence":0,"period":216,"date":"2018-03-12"},{"id":847030,"mark":4,"student":11561,"lesson_info":{"id":11342,"subject":532,"teacher":1122,"class":719},"presence":0,"period":216,"date":"2018-03-17"},{"id":847031,"mark":null,"student":11561,"lesson_info":{"id":11342,"subject":532,"teacher":1122,"class":719},"presence":1,"period":216,"date":"2018-03-24"},{"id":847032,"mark":null,"student":11561,"lesson_info":{"id":11342,"subject":532,"teacher":1122,"class":719},"presence":1,"period":216,"date":"2018-03-24"},{"id":847033,"mark":null,"student":11561,"lesson_info":{"id":11342,"subject":532,"teacher":1122,"class":719},"presence":1,"period":216,"date":"2018-04-02"},{"id":847034,"mark":null,"student":11561,"lesson_info":{"id":11342,"subject":532,"teacher":1122,"class":719},"presence":1,"period":216,"date":"2018-04-02"},{"id":847035,"mark":null,"student":11561,"lesson_info":{"id":11342,"subject":532,"teacher":1122,"class":719},"presence":1,"period":216,"date":"2018-04-07"},{"id":847036,"mark":null,"student":11561,"lesson_info":{"id":11342,"subject":532,"teacher":1122,"class":719},"presence":1,"period":216,"date":"2018-04-07"},{"id":847037,"mark":5,"student":11561,"lesson_info":{"id":11342,"subject":532,"teacher":1122,"class":719},"presence":0,"period":216,"date":"2018-04-09"},{"id":847038,"mark":5,"student":11561,"lesson_info":{"id":11342,"subject":532,"teacher":1122,"class":719},"presence":0,"period":216,"date":"2018-04-14"},{"id":847039,"mark":5,"student":11561,"lesson_info":{"id":11342,"subject":532,"teacher":1122,"class":719},"presence":0,"period":216,"date":"2018-04-16"},{"id":847040,"mark":5,"student":11561,"lesson_info":{"id":11342,"subject":532,"teacher":1122,"class":719},"presence":0,"period":216,"date":"2018-04-21"},{"id":847041,"mark":4,"student":11561,"lesson_info":{"id":11342,"subject":532,"teacher":1122,"class":719},"presence":0,"period":216,"date":"2018-04-23"},{"id":847042,"mark":null,"student":11561,"lesson_info":{"id":11342,"subject":532,"teacher":1122,"class":719},"presence":1,"period":216,"date":"2018-04-28"},{"id":847043,"mark":null,"student":11561,"lesson_info":{"id":11342,"subject":532,"teacher":1122,"class":719},"presence":1,"period":216,"date":"2018-04-28"},{"id":847044,"mark":4,"student":11561,"lesson_info":{"id":11342,"subject":532,"teacher":1122,"class":719},"presence":0,"period":216,"date":"2018-05-07"},{"id":847045,"mark":4,"student":11561,"lesson_info":{"id":11342,"subject":532,"teacher":1122,"class":719},"presence":0,"period":216,"date":"2018-05-12"},{"id":847046,"mark":5,"student":11561,"lesson_info":{"id":11342,"subject":532,"teacher":1122,"class":719},"presence":0,"period":216,"date":"2018-05-14"},{"id":847565,"mark":4,"student":11561,"lesson_info":{"id":11343,"subject":524,"teacher":1153,"class":719},"presence":0,"period":216,"date":"2018-01-12"},{"id":847566,"mark":4,"student":11561,"lesson_info":{"id":11343,"subject":524,"teacher":1153,"class":719},"presence":0,"period":216,"date":"2018-01-26"},{"id":847567,"mark":4,"student":11561,"lesson_info":{"id":11343,"subject":524,"teacher":1153,"class":719},"presence":0,"period":216,"date":"2018-02-02"},{"id":847568,"mark":4,"student":11561,"lesson_info":{"id":11343,"subject":524,"teacher":1153,"class":719},"presence":0,"period":216,"date":"2018-02-16"},{"id":847569,"mark":4,"student":11561,"lesson_info":{"id":11343,"subject":524,"teacher":1153,"class":719},"presence":0,"period":216,"date":"2018-03-21"},{"id":847570,"mark":4,"student":11561,"lesson_info":{"id":11343,"subject":524,"teacher":1153,"class":719},"presence":0,"period":216,"date":"2018-04-04"},{"id":847571,"mark":4,"student":11561,"lesson_info":{"id":11343,"subject":524,"teacher":1153,"class":719},"presence":0,"period":216,"date":"2018-04-06"},{"id":847572,"mark":null,"student":11561,"lesson_info":{"id":11343,"subject":524,"teacher":1153,"class":719},"presence":1,"period":216,"date":"2018-04-11"},{"id":847573,"mark":null,"student":11561,"lesson_info":{"id":11343,"subject":524,"teacher":1153,"class":719},"presence":1,"period":216,"date":"2018-04-11"},{"id":847574,"mark":4,"student":11561,"lesson_info":{"id":11343,"subject":524,"teacher":1153,"class":719},"presence":0,"period":216,"date":"2018-04-20"},{"id":847575,"mark":4,"student":11561,"lesson_info":{"id":11343,"subject":524,"teacher":1153,"class":719},"presence":0,"period":216,"date":"2018-05-02"},{"id":847576,"mark":null,"student":11561,"lesson_info":{"id":11343,"subject":524,"teacher":1153,"class":719},"presence":1,"period":216,"date":"2018-05-04"},{"id":847577,"mark":null,"student":11561,"lesson_info":{"id":11343,"subject":524,"teacher":1153,"class":719},"presence":1,"period":216,"date":"2018-05-04"},{"id":847578,"mark":4,"student":11561,"lesson_info":{"id":11343,"subject":524,"teacher":1153,"class":719},"presence":0,"period":216,"date":"2018-05-16"},{"id":847856,"mark":4,"student":11561,"lesson_info":{"id":11344,"subject":526,"teacher":1134,"class":719},"presence":0,"period":216,"date":"2018-02-01"},{"id":847857,"mark":4,"student":11561,"lesson_info":{"id":11344,"subject":526,"teacher":1134,"class":719},"presence":0,"period":216,"date":"2018-03-01"},{"id":847858,"mark":5,"student":11561,"lesson_info":{"id":11344,"subject":526,"teacher":1134,"class":719},"presence":0,"period":216,"date":"2018-03-15"},{"id":847859,"mark":5,"student":11561,"lesson_info":{"id":11344,"subject":526,"teacher":1134,"class":719},"presence":0,"period":216,"date":"2018-04-05"},{"id":847860,"mark":4,"student":11561,"lesson_info":{"id":11344,"subject":526,"teacher":1134,"class":719},"presence":0,"period":216,"date":"2018-04-19"},{"id":847861,"mark":5,"student":11561,"lesson_info":{"id":11344,"subject":526,"teacher":1134,"class":719},"presence":0,"period":216,"date":"2018-04-19"},{"id":847862,"mark":4,"student":11561,"lesson_info":{"id":11344,"subject":526,"teacher":1134,"class":719},"presence":0,"period":216,"date":"2018-05-03"},{"id":847863,"mark":5,"student":11561,"lesson_info":{"id":11344,"subject":526,"teacher":1134,"class":719},"presence":0,"period":216,"date":"2018-05-17"},{"id":847864,"mark":5,"student":11561,"lesson_info":{"id":11344,"subject":526,"teacher":1134,"class":719},"presence":0,"period":216,"date":"2018-05-17"},{"id":848031,"mark":null,"student":11561,"lesson_info":{"id":11345,"subject":527,"teacher":1136,"class":719},"presence":1,"period":216,"date":"2018-01-22"},{"id":848032,"mark":null,"student":11561,"lesson_info":{"id":11345,"subject":527,"teacher":1136,"class":719},"presence":1,"period":216,"date":"2018-01-22"},{"id":848033,"mark":5,"student":11561,"lesson_info":{"id":11345,"subject":527,"teacher":1136,"class":719},"presence":0,"period":216,"date":"2018-02-03"},{"id":848034,"mark":null,"student":11561,"lesson_info":{"id":11345,"subject":527,"teacher":1136,"class":719},"presence":1,"period":216,"date":"2018-03-03"},{"id":848035,"mark":null,"student":11561,"lesson_info":{"id":11345,"subject":527,"teacher":1136,"class":719},"presence":1,"period":216,"date":"2018-03-03"},{"id":848036,"mark":4,"student":11561,"lesson_info":{"id":11345,"subject":527,"teacher":1136,"class":719},"presence":0,"period":216,"date":"2018-03-17"},{"id":848037,"mark":4,"student":11561,"lesson_info":{"id":11345,"subject":527,"teacher":1136,"class":719},"presence":0,"period":216,"date":"2018-03-17"},{"id":848038,"mark":null,"student":11561,"lesson_info":{"id":11345,"subject":527,"teacher":1136,"class":719},"presence":1,"period":216,"date":"2018-04-07"},{"id":848039,"mark":null,"student":11561,"lesson_info":{"id":11345,"subject":527,"teacher":1136,"class":719},"presence":1,"period":216,"date":"2018-04-07"},{"id":848040,"mark":5,"student":11561,"lesson_info":{"id":11345,"subject":527,"teacher":1136,"class":719},"presence":0,"period":216,"date":"2018-04-21"},{"id":848041,"mark":4,"student":11561,"lesson_info":{"id":11345,"subject":527,"teacher":1136,"class":719},"presence":0,"period":216,"date":"2018-05-05"},{"id":848042,"mark":5,"student":11561,"lesson_info":{"id":11345,"subject":527,"teacher":1136,"class":719},"presence":0,"period":216,"date":"2018-05-05"},{"id":848043,"mark":5,"student":11561,"lesson_info":{"id":11345,"subject":527,"teacher":1136,"class":719},"presence":0,"period":216,"date":"2018-05-19"},{"id":848282,"mark":4,"student":11561,"lesson_info":{"id":11346,"subject":533,"teacher":1122,"class":719},"presence":0,"period":216,"date":"2018-01-17"},{"id":848283,"mark":5,"student":11561,"lesson_info":{"id":11346,"subject":533,"teacher":1122,"class":719},"presence":0,"period":216,"date":"2018-01-24"},{"id":848284,"mark":4,"student":11561,"lesson_info":{"id":11346,"subject":533,"teacher":1122,"class":719},"presence":0,"period":216,"date":"2018-01-31"},{"id":848285,"mark":4,"student":11561,"lesson_info":{"id":11346,"subject":533,"teacher":1122,"class":719},"presence":0,"period":216,"date":"2018-02-14"},{"id":848286,"mark":null,"student":11561,"lesson_info":{"id":11346,"subject":533,"teacher":1122,"class":719},"presence":1,"period":216,"date":"2018-02-28"},{"id":848287,"mark":null,"student":11561,"lesson_info":{"id":11346,"subject":533,"teacher":1122,"class":719},"presence":1,"period":216,"date":"2018-02-28"},{"id":848288,"mark":4,"student":11561,"lesson_info":{"id":11346,"subject":533,"teacher":1122,"class":719},"presence":0,"period":216,"date":"2018-03-14"},{"id":848289,"mark":4,"student":11561,"lesson_info":{"id":11346,"subject":533,"teacher":1122,"class":719},"presence":0,"period":216,"date":"2018-04-13"},{"id":848290,"mark":5,"student":11561,"lesson_info":{"id":11346,"subject":533,"teacher":1122,"class":719},"presence":0,"period":216,"date":"2018-04-18"},{"id":848291,"mark":5,"student":11561,"lesson_info":{"id":11346,"subject":533,"teacher":1122,"class":719},"presence":0,"period":216,"date":"2018-04-27"},{"id":848292,"mark":4,"student":11561,"lesson_info":{"id":11346,"subject":533,"teacher":1122,"class":719},"presence":0,"period":216,"date":"2018-05-02"},{"id":848293,"mark":4,"student":11561,"lesson_info":{"id":11346,"subject":533,"teacher":1122,"class":719},"presence":0,"period":216,"date":"2018-05-16"},{"id":848542,"mark":4,"student":11561,"lesson_info":{"id":11347,"subject":528,"teacher":1115,"class":719},"presence":0,"period":216,"date":"2018-01-23"},{"id":848543,"mark":null,"student":11561,"lesson_info":{"id":11347,"subject":528,"teacher":1115,"class":719},"presence":1,"period":216,"date":"2018-02-06"},{"id":848544,"mark":null,"student":11561,"lesson_info":{"id":11347,"subject":528,"teacher":1115,"class":719},"presence":1,"period":216,"date":"2018-02-06"},{"id":848545,"mark":5,"student":11561,"lesson_info":{"id":11347,"subject":528,"teacher":1115,"class":719},"presence":0,"period":216,"date":"2018-02-20"},{"id":848546,"mark":5,"student":11561,"lesson_info":{"id":11347,"subject":528,"teacher":1115,"class":719},"presence":0,"period":216,"date":"2018-03-06"},{"id":848547,"mark":4,"student":11561,"lesson_info":{"id":11347,"subject":528,"teacher":1115,"class":719},"presence":0,"period":216,"date":"2018-03-06"},{"id":848548,"mark":null,"student":11561,"lesson_info":{"id":11347,"subject":528,"teacher":1115,"class":719},"presence":1,"period":216,"date":"2018-03-20"},{"id":848549,"mark":null,"student":11561,"lesson_info":{"id":11347,"subject":528,"teacher":1115,"class":719},"presence":1,"period":216,"date":"2018-03-20"},{"id":848550,"mark":null,"student":11561,"lesson_info":{"id":11347,"subject":528,"teacher":1115,"class":719},"presence":1,"period":216,"date":"2018-04-10"},{"id":848551,"mark":null,"student":11561,"lesson_info":{"id":11347,"subject":528,"teacher":1115,"class":719},"presence":1,"period":216,"date":"2018-04-10"},{"id":848552,"mark":5,"student":11561,"lesson_info":{"id":11347,"subject":528,"teacher":1115,"class":719},"presence":0,"period":216,"date":"2018-05-22"},{"id":848772,"mark":4,"student":11561,"lesson_info":{"id":11348,"subject":529,"teacher":1065,"class":719},"presence":0,"period":216,"date":"2018-01-23"},{"id":848773,"mark":4,"student":11561,"lesson_info":{"id":11348,"subject":529,"teacher":1065,"class":719},"presence":0,"period":216,"date":"2018-02-02"},{"id":848774,"mark":3,"student":11561,"lesson_info":{"id":11348,"subject":529,"teacher":1065,"class":719},"presence":0,"period":216,"date":"2018-03-02"},{"id":848775,"mark":4,"student":11561,"lesson_info":{"id":11348,"subject":529,"teacher":1065,"class":719},"presence":0,"period":216,"date":"2018-03-16"},{"id":848776,"mark":null,"student":11561,"lesson_info":{"id":11348,"subject":529,"teacher":1065,"class":719},"presence":1,"period":216,"date":"2018-04-06"},{"id":848777,"mark":null,"student":11561,"lesson_info":{"id":11348,"subject":529,"teacher":1065,"class":719},"presence":1,"period":216,"date":"2018-04-06"},{"id":848778,"mark":3,"student":11561,"lesson_info":{"id":11348,"subject":529,"teacher":1065,"class":719},"presence":0,"period":216,"date":"2018-04-27"},{"id":848779,"mark":null,"student":11561,"lesson_info":{"id":11348,"subject":529,"teacher":1065,"class":719},"presence":1,"period":216,"date":"2018-05-04"},{"id":848780,"mark":null,"student":11561,"lesson_info":{"id":11348,"subject":529,"teacher":1065,"class":719},"presence":1,"period":216,"date":"2018-05-04"},{"id":848781,"mark":3,"student":11561,"lesson_info":{"id":11348,"subject":529,"teacher":1065,"class":719},"presence":0,"period":216,"date":"2018-05-11"},{"id":848782,"mark":4,"student":11561,"lesson_info":{"id":11348,"subject":529,"teacher":1065,"class":719},"presence":0,"period":216,"date":"2018-05-18"},{"id":848973,"mark":4,"student":11561,"lesson_info":{"id":11349,"subject":535,"teacher":1082,"class":719},"presence":0,"period":216,"date":"2018-01-20"},{"id":848974,"mark":null,"student":11561,"lesson_info":{"id":11349,"subject":535,"teacher":1082,"class":719},"presence":1,"period":216,"date":"2018-02-13"},{"id":848975,"mark":null,"student":11561,"lesson_info":{"id":11349,"subject":535,"teacher":1082,"class":719},"presence":1,"period":216,"date":"2018-02-13"},{"id":848976,"mark":null,"student":11561,"lesson_info":{"id":11349,"subject":535,"teacher":1082,"class":719},"presence":1,"period":216,"date":"2018-02-27"},{"id":848977,"mark":null,"student":11561,"lesson_info":{"id":11349,"subject":535,"teacher":1082,"class":719},"presence":1,"period":216,"date":"2018-02-27"},{"id":848978,"mark":5,"student":11561,"lesson_info":{"id":11349,"subject":535,"teacher":1082,"class":719},"presence":0,"period":216,"date":"2018-03-13"},{"id":848979,"mark":5,"student":11561,"lesson_info":{"id":11349,"subject":535,"teacher":1082,"class":719},"presence":0,"period":216,"date":"2018-04-03"},{"id":848980,"mark":5,"student":11561,"lesson_info":{"id":11349,"subject":535,"teacher":1082,"class":719},"presence":0,"period":216,"date":"2018-05-15"},{"id":849119,"mark":4,"student":11561,"lesson_info":{"id":11350,"subject":530,"teacher":1065,"class":719},"presence":0,"period":216,"date":"2018-01-24"},{"id":849120,"mark":4,"student":11561,"lesson_info":{"id":11350,"subject":530,"teacher":1065,"class":719},"presence":0,"period":216,"date":"2018-02-07"},{"id":849121,"mark":4,"student":11561,"lesson_info":{"id":11350,"subject":530,"teacher":1065,"class":719},"presence":0,"period":216,"date":"2018-02-21"},{"id":849122,"mark":5,"student":11561,"lesson_info":{"id":11350,"subject":530,"teacher":1065,"class":719},"presence":0,"period":216,"date":"2018-03-07"},{"id":849123,"mark":5,"student":11561,"lesson_info":{"id":11350,"subject":530,"teacher":1065,"class":719},"presence":0,"period":216,"date":"2018-04-04"},{"id":849124,"mark":5,"student":11561,"lesson_info":{"id":11350,"subject":530,"teacher":1065,"class":719},"presence":0,"period":216,"date":"2018-04-04"},{"id":849125,"mark":5,"student":11561,"lesson_info":{"id":11350,"subject":530,"teacher":1065,"class":719},"presence":0,"period":216,"date":"2018-04-18"},{"id":849126,"mark":5,"student":11561,"lesson_info":{"id":11350,"subject":530,"teacher":1065,"class":719},"presence":0,"period":216,"date":"2018-04-18"},{"id":849127,"mark":4,"student":11561,"lesson_info":{"id":11350,"subject":530,"teacher":1065,"class":719},"presence":0,"period":216,"date":"2018-05-16"},{"id":849128,"mark":5,"student":11561,"lesson_info":{"id":11350,"subject":530,"teacher":1065,"class":719},"presence":0,"period":216,"date":"2018-05-16"},{"id":849295,"mark":null,"student":11561,"lesson_info":{"id":11351,"subject":546,"teacher":1073,"class":719},"presence":1,"period":216,"date":"2018-01-18"},{"id":849296,"mark":null,"student":11561,"lesson_info":{"id":11351,"subject":546,"teacher":1073,"class":719},"presence":1,"period":216,"date":"2018-01-18"},{"id":849297,"mark":null,"student":11561,"lesson_info":{"id":11351,"subject":546,"teacher":1073,"class":719},"presence":1,"period":216,"date":"2018-02-06"},{"id":849298,"mark":null,"student":11561,"lesson_info":{"id":11351,"subject":546,"teacher":1073,"class":719},"presence":1,"period":216,"date":"2018-02-06"},{"id":849299,"mark":4,"student":11561,"lesson_info":{"id":11351,"subject":546,"teacher":1073,"class":719},"presence":0,"period":216,"date":"2018-02-20"},{"id":849300,"mark":null,"student":11561,"lesson_info":{"id":11351,"subject":546,"teacher":1073,"class":719},"presence":1,"period":216,"date":"2018-03-20"},{"id":849301,"mark":null,"student":11561,"lesson_info":{"id":11351,"subject":546,"teacher":1073,"class":719},"presence":1,"period":216,"date":"2018-03-20"},{"id":849302,"mark":5,"student":11561,"lesson_info":{"id":11351,"subject":546,"teacher":1073,"class":719},"presence":0,"period":216,"date":"2018-04-10"},{"id":849303,"mark":null,"student":11561,"lesson_info":{"id":11351,"subject":546,"teacher":1073,"class":719},"presence":1,"period":216,"date":"2018-04-24"},{"id":849304,"mark":null,"student":11561,"lesson_info":{"id":11351,"subject":546,"teacher":1073,"class":719},"presence":1,"period":216,"date":"2018-04-24"},{"id":849305,"mark":4,"student":11561,"lesson_info":{"id":11351,"subject":546,"teacher":1073,"class":719},"presence":0,"period":216,"date":"2018-05-08"},{"id":849306,"mark":5,"student":11561,"lesson_info":{"id":11351,"subject":546,"teacher":1073,"class":719},"presence":0,"period":216,"date":"2018-05-22"},{"id":849551,"mark":5,"student":11561,"lesson_info":{"id":11352,"subject":531,"teacher":1068,"class":719},"presence":0,"period":216,"date":"2018-01-16"},{"id":849552,"mark":5,"student":11561,"lesson_info":{"id":11352,"subject":531,"teacher":1068,"class":719},"presence":0,"period":216,"date":"2018-01-20"},{"id":849553,"mark":4,"student":11561,"lesson_info":{"id":11352,"subject":531,"teacher":1068,"class":719},"presence":0,"period":216,"date":"2018-02-10"},{"id":849554,"mark":null,"student":11561,"lesson_info":{"id":11352,"subject":531,"teacher":1068,"class":719},"presence":1,"period":216,"date":"2018-02-17"},{"id":849555,"mark":null,"student":11561,"lesson_info":{"id":11352,"subject":531,"teacher":1068,"class":719},"presence":1,"period":216,"date":"2018-02-17"},{"id":849556,"mark":5,"student":11561,"lesson_info":{"id":11352,"subject":531,"teacher":1068,"class":719},"presence":0,"period":216,"date":"2018-02-21"},{"id":849557,"mark":4,"student":11561,"lesson_info":{"id":11352,"subject":531,"teacher":1068,"class":719},"presence":0,"period":216,"date":"2018-02-24"},{"id":849558,"mark":null,"student":11561,"lesson_info":{"id":11352,"subject":531,"teacher":1068,"class":719},"presence":1,"period":216,"date":"2018-03-07"},{"id":849559,"mark":5,"student":11561,"lesson_info":{"id":11352,"subject":531,"teacher":1068,"class":719},"presence":0,"period":216,"date":"2018-03-17"},{"id":849560,"mark":5,"student":11561,"lesson_info":{"id":11352,"subject":531,"teacher":1068,"class":719},"presence":0,"period":216,"date":"2018-03-21"},{"id":849561,"mark":4,"student":11561,"lesson_info":{"id":11352,"subject":531,"teacher":1068,"class":719},"presence":0,"period":216,"date":"2018-04-11"},{"id":849562,"mark":5,"student":11561,"lesson_info":{"id":11352,"subject":531,"teacher":1068,"class":719},"presence":0,"period":216,"date":"2018-04-25"},{"id":849563,"mark":5,"student":11561,"lesson_info":{"id":11352,"subject":531,"teacher":1068,"class":719},"presence":0,"period":216,"date":"2018-05-05"},{"id":849564,"mark":5,"student":11561,"lesson_info":{"id":11352,"subject":531,"teacher":1068,"class":719},"presence":0,"period":216,"date":"2018-05-12"},{"id":849565,"mark":4,"student":11561,"lesson_info":{"id":11352,"subject":531,"teacher":1068,"class":719},"presence":0,"period":216,"date":"2018-05-19"},{"id":849566,"mark":4,"student":11561,"lesson_info":{"id":11352,"subject":531,"teacher":1068,"class":719},"presence":0,"period":216,"date":"2018-05-23"},{"id":849567,"mark":5,"student":11561,"lesson_info":{"id":11352,"subject":531,"teacher":1068,"class":719},"presence":0,"period":216,"date":"2018-05-23"},{"id":849956,"mark":5,"student":11561,"lesson_info":{"id":11353,"subject":514,"teacher":1068,"class":719},"presence":0,"period":216,"date":"2018-01-12"},{"id":849957,"mark":4,"student":11561,"lesson_info":{"id":11353,"subject":514,"teacher":1068,"class":719},"presence":0,"period":216,"date":"2018-01-26"},{"id":849958,"mark":4,"student":11561,"lesson_info":{"id":11353,"subject":514,"teacher":1068,"class":719},"presence":0,"period":216,"date":"2018-01-26"},{"id":849959,"mark":4,"student":11561,"lesson_info":{"id":11353,"subject":514,"teacher":1068,"class":719},"presence":0,"period":216,"date":"2018-02-01"},{"id":849960,"mark":4,"student":11561,"lesson_info":{"id":11353,"subject":514,"teacher":1068,"class":719},"presence":0,"period":216,"date":"2018-02-01"},{"id":849961,"mark":4,"student":11561,"lesson_info":{"id":11353,"subject":514,"teacher":1068,"class":719},"presence":0,"period":216,"date":"2018-02-08"},{"id":849962,"mark":4,"student":11561,"lesson_info":{"id":11353,"subject":514,"teacher":1068,"class":719},"presence":0,"period":216,"date":"2018-02-08"},{"id":849963,"mark":4,"student":11561,"lesson_info":{"id":11353,"subject":514,"teacher":1068,"class":719},"presence":0,"period":216,"date":"2018-03-01"},{"id":849964,"mark":4,"student":11561,"lesson_info":{"id":11353,"subject":514,"teacher":1068,"class":719},"presence":0,"period":216,"date":"2018-03-01"},{"id":849965,"mark":4,"student":11561,"lesson_info":{"id":11353,"subject":514,"teacher":1068,"class":719},"presence":0,"period":216,"date":"2018-03-22"},{"id":849966,"mark":5,"student":11561,"lesson_info":{"id":11353,"subject":514,"teacher":1068,"class":719},"presence":0,"period":216,"date":"2018-04-05"},{"id":849967,"mark":5,"student":11561,"lesson_info":{"id":11353,"subject":514,"teacher":1068,"class":719},"presence":0,"period":216,"date":"2018-04-12"},{"id":849968,"mark":4,"student":11561,"lesson_info":{"id":11353,"subject":514,"teacher":1068,"class":719},"presence":0,"period":216,"date":"2018-04-19"},{"id":849969,"mark":4,"student":11561,"lesson_info":{"id":11353,"subject":514,"teacher":1068,"class":719},"presence":0,"period":216,"date":"2018-04-19"},{"id":849970,"mark":4,"student":11561,"lesson_info":{"id":11353,"subject":514,"teacher":1068,"class":719},"presence":0,"period":216,"date":"2018-04-26"},{"id":849971,"mark":5,"student":11561,"lesson_info":{"id":11353,"subject":514,"teacher":1068,"class":719},"presence":0,"period":216,"date":"2018-05-03"},{"id":849972,"mark":4,"student":11561,"lesson_info":{"id":11353,"subject":514,"teacher":1068,"class":719},"presence":0,"period":216,"date":"2018-05-03"},{"id":849973,"mark":4,"student":11561,"lesson_info":{"id":11353,"subject":514,"teacher":1068,"class":719},"presence":0,"period":216,"date":"2018-05-17"},{"id":849974,"mark":4,"student":11561,"lesson_info":{"id":11353,"subject":514,"teacher":1068,"class":719},"presence":0,"period":216,"date":"2018-05-17"},{"id":849975,"mark":4,"student":11561,"lesson_info":{"id":11353,"subject":514,"teacher":1068,"class":719},"presence":0,"period":216,"date":"2018-05-24"},{"id":849976,"mark":4,"student":11561,"lesson_info":{"id":11353,"subject":514,"teacher":1068,"class":719},"presence":0,"period":216,"date":"2018-05-24"},{"id":850458,"mark":4,"student":11561,"lesson_info":{"id":11354,"subject":534,"teacher":1080,"class":719},"presence":0,"period":216,"date":"2018-01-17"},{"id":850459,"mark":2,"student":11561,"lesson_info":{"id":11354,"subject":534,"teacher":1080,"class":719},"presence":0,"period":216,"date":"2018-01-18"},{"id":850460,"mark":3,"student":11561,"lesson_info":{"id":11354,"subject":534,"teacher":1080,"class":719},"presence":0,"period":216,"date":"2018-01-23"},{"id":850461,"mark":3,"student":11561,"lesson_info":{"id":11354,"subject":534,"teacher":1080,"class":719},"presence":0,"period":216,"date":"2018-01-25"},{"id":850462,"mark":3,"student":11561,"lesson_info":{"id":11354,"subject":534,"teacher":1080,"class":719},"presence":0,"period":216,"date":"2018-01-31"},{"id":850463,"mark":null,"student":11561,"lesson_info":{"id":11354,"subject":534,"teacher":1080,"class":719},"presence":1,"period":216,"date":"2018-02-06"},{"id":850464,"mark":null,"student":11561,"lesson_info":{"id":11354,"subject":534,"teacher":1080,"class":719},"presence":1,"period":216,"date":"2018-02-06"},{"id":850465,"mark":null,"student":11561,"lesson_info":{"id":11354,"subject":534,"teacher":1080,"class":719},"presence":1,"period":216,"date":"2018-02-07"},{"id":850466,"mark":null,"student":11561,"lesson_info":{"id":11354,"subject":534,"teacher":1080,"class":719},"presence":1,"period":216,"date":"2018-02-07"},{"id":850467,"mark":4,"student":11561,"lesson_info":{"id":11354,"subject":534,"teacher":1080,"class":719},"presence":0,"period":216,"date":"2018-02-08"},{"id":850468,"mark":5,"student":11561,"lesson_info":{"id":11354,"subject":534,"teacher":1080,"class":719},"presence":0,"period":216,"date":"2018-02-13"},{"id":850469,"mark":null,"student":11561,"lesson_info":{"id":11354,"subject":534,"teacher":1080,"class":719},"presence":1,"period":216,"date":"2018-02-22"},{"id":850470,"mark":null,"student":11561,"lesson_info":{"id":11354,"subject":534,"teacher":1080,"class":719},"presence":1,"period":216,"date":"2018-02-27"},{"id":850471,"mark":null,"student":11561,"lesson_info":{"id":11354,"subject":534,"teacher":1080,"class":719},"presence":1,"period":216,"date":"2018-02-27"},{"id":850472,"mark":2,"student":11561,"lesson_info":{"id":11354,"subject":534,"teacher":1080,"class":719},"presence":0,"period":216,"date":"2018-03-06"},{"id":850473,"mark":null,"student":11561,"lesson_info":{"id":11354,"subject":534,"teacher":1080,"class":719},"presence":1,"period":216,"date":"2018-03-07"},{"id":850474,"mark":null,"student":11561,"lesson_info":{"id":11354,"subject":534,"teacher":1080,"class":719},"presence":1,"period":216,"date":"2018-03-07"},{"id":850475,"mark":5,"student":11561,"lesson_info":{"id":11354,"subject":534,"teacher":1080,"class":719},"presence":0,"period":216,"date":"2018-03-14"},{"id":850476,"mark":null,"student":11561,"lesson_info":{"id":11354,"subject":534,"teacher":1080,"class":719},"presence":1,"period":216,"date":"2018-03-20"},{"id":850477,"mark":null,"student":11561,"lesson_info":{"id":11354,"subject":534,"teacher":1080,"class":719},"presence":1,"period":216,"date":"2018-03-20"},{"id":850478,"mark":3,"student":11561,"lesson_info":{"id":11354,"subject":534,"teacher":1080,"class":719},"presence":0,"period":216,"date":"2018-03-22"},{"id":850479,"mark":null,"student":11561,"lesson_info":{"id":11354,"subject":534,"teacher":1080,"class":719},"presence":1,"period":216,"date":"2018-04-10"},{"id":850480,"mark":null,"student":11561,"lesson_info":{"id":11354,"subject":534,"teacher":1080,"class":719},"presence":1,"period":216,"date":"2018-04-10"},{"id":850481,"mark":3,"student":11561,"lesson_info":{"id":11354,"subject":534,"teacher":1080,"class":719},"presence":0,"period":216,"date":"2018-04-17"},{"id":850482,"mark":5,"student":11561,"lesson_info":{"id":11354,"subject":534,"teacher":1080,"class":719},"presence":0,"period":216,"date":"2018-04-25"},{"id":850483,"mark":4,"student":11561,"lesson_info":{"id":11354,"subject":534,"teacher":1080,"class":719},"presence":0,"period":216,"date":"2018-05-10"},{"id":850484,"mark":5,"student":11561,"lesson_info":{"id":11354,"subject":534,"teacher":1080,"class":719},"presence":0,"period":216,"date":"2018-05-21"},{"id":850976,"mark":5,"student":11561,"lesson_info":{"id":11355,"subject":515,"teacher":1102,"class":719},"presence":0,"period":216,"date":"2018-01-18"},{"id":850977,"mark":5,"student":11561,"lesson_info":{"id":11355,"subject":515,"teacher":1102,"class":719},"presence":0,"period":216,"date":"2018-01-18"},{"id":850978,"mark":null,"student":11561,"lesson_info":{"id":11355,"subject":515,"teacher":1102,"class":719},"presence":1,"period":216,"date":"2018-02-08"},{"id":850979,"mark":null,"student":11561,"lesson_info":{"id":11355,"subject":515,"teacher":1102,"class":719},"presence":1,"period":216,"date":"2018-02-08"},{"id":850980,"mark":null,"student":11561,"lesson_info":{"id":11355,"subject":515,"teacher":1102,"class":719},"presence":1,"period":216,"date":"2018-02-15"},{"id":850981,"mark":null,"student":11561,"lesson_info":{"id":11355,"subject":515,"teacher":1102,"class":719},"presence":1,"period":216,"date":"2018-02-15"},{"id":850982,"mark":5,"student":11561,"lesson_info":{"id":11355,"subject":515,"teacher":1102,"class":719},"presence":0,"period":216,"date":"2018-02-22"},{"id":850983,"mark":null,"student":11561,"lesson_info":{"id":11355,"subject":515,"teacher":1102,"class":719},"presence":1,"period":216,"date":"2018-03-15"},{"id":850984,"mark":null,"student":11561,"lesson_info":{"id":11355,"subject":515,"teacher":1102,"class":719},"presence":1,"period":216,"date":"2018-03-15"},{"id":850985,"mark":4,"student":11561,"lesson_info":{"id":11355,"subject":515,"teacher":1102,"class":719},"presence":0,"period":216,"date":"2018-04-05"},{"id":850986,"mark":4,"student":11561,"lesson_info":{"id":11355,"subject":515,"teacher":1102,"class":719},"presence":0,"period":216,"date":"2018-04-12"},{"id":850987,"mark":5,"student":11561,"lesson_info":{"id":11355,"subject":515,"teacher":1102,"class":719},"presence":0,"period":216,"date":"2018-04-19"},{"id":850988,"mark":5,"student":11561,"lesson_info":{"id":11355,"subject":515,"teacher":1102,"class":719},"presence":0,"period":216,"date":"2018-04-26"},{"id":850989,"mark":null,"student":11561,"lesson_info":{"id":11355,"subject":515,"teacher":1102,"class":719},"presence":1,"period":216,"date":"2018-05-17"},{"id":850990,"mark":null,"student":11561,"lesson_info":{"id":11355,"subject":515,"teacher":1102,"class":719},"presence":1,"period":216,"date":"2018-05-17"},{"id":851273,"mark":null,"student":11561,"lesson_info":{"id":11356,"subject":536,"teacher":1081,"class":719},"presence":1,"period":216,"date":"2018-02-24"},{"id":851274,"mark":null,"student":11561,"lesson_info":{"id":11356,"subject":536,"teacher":1081,"class":719},"presence":1,"period":216,"date":"2018-02-24"},{"id":851275,"mark":5,"student":11561,"lesson_info":{"id":11356,"subject":536,"teacher":1081,"class":719},"presence":0,"period":216,"date":"2018-03-24"},{"id":851276,"mark":null,"student":11561,"lesson_info":{"id":11356,"subject":536,"teacher":1081,"class":719},"presence":1,"period":216,"date":"2018-04-28"},{"id":851277,"mark":null,"student":11561,"lesson_info":{"id":11356,"subject":536,"teacher":1081,"class":719},"presence":1,"period":216,"date":"2018-04-28"},{"id":851278,"mark":5,"student":11561,"lesson_info":{"id":11356,"subject":536,"teacher":1081,"class":719},"presence":0,"period":216,"date":"2018-05-10"},{"id":851279,"mark":5,"student":11561,"lesson_info":{"id":11356,"subject":536,"teacher":1081,"class":719},"presence":0,"period":216,"date":"2018-05-10"},{"id":851280,"mark":5,"student":11561,"lesson_info":{"id":11356,"subject":536,"teacher":1081,"class":719},"presence":0,"period":216,"date":"2018-05-18"},{"id":851443,"mark":null,"student":11561,"lesson_info":{"id":11357,"subject":516,"teacher":1065,"class":719},"presence":1,"period":216,"date":"2018-01-18"},{"id":851444,"mark":4,"student":11561,"lesson_info":{"id":11357,"subject":516,"teacher":1065,"class":719},"presence":0,"period":216,"date":"2018-01-30"},{"id":851445,"mark":5,"student":11561,"lesson_info":{"id":11357,"subject":516,"teacher":1065,"class":719},"presence":0,"period":216,"date":"2018-01-30"},{"id":851446,"mark":5,"student":11561,"lesson_info":{"id":11357,"subject":516,"teacher":1065,"class":719},"presence":0,"period":216,"date":"2018-02-13"},{"id":851447,"mark":null,"student":11561,"lesson_info":{"id":11357,"subject":516,"teacher":1065,"class":719},"presence":1,"period":216,"date":"2018-02-27"},{"id":851448,"mark":null,"student":11561,"lesson_info":{"id":11357,"subject":516,"teacher":1065,"class":719},"presence":1,"period":216,"date":"2018-02-27"},{"id":851449,"mark":4,"student":11561,"lesson_info":{"id":11357,"subject":516,"teacher":1065,"class":719},"presence":0,"period":216,"date":"2018-03-13"},{"id":851450,"mark":null,"student":11561,"lesson_info":{"id":11357,"subject":516,"teacher":1065,"class":719},"presence":1,"period":216,"date":"2018-04-03"},{"id":851451,"mark":null,"student":11561,"lesson_info":{"id":11357,"subject":516,"teacher":1065,"class":719},"presence":1,"period":216,"date":"2018-04-03"},{"id":851452,"mark":5,"student":11561,"lesson_info":{"id":11357,"subject":516,"teacher":1065,"class":719},"presence":0,"period":216,"date":"2018-04-17"},{"id":851453,"mark":5,"student":11561,"lesson_info":{"id":11357,"subject":516,"teacher":1065,"class":719},"presence":0,"period":216,"date":"2018-05-08"},{"id":851454,"mark":4,"student":11561,"lesson_info":{"id":11357,"subject":516,"teacher":1065,"class":719},"presence":0,"period":216,"date":"2018-05-15"},{"id":851708,"mark":4,"student":11561,"lesson_info":{"id":11358,"subject":554,"teacher":1115,"class":719},"presence":0,"period":216,"date":"2018-01-17"},{"id":851709,"mark":5,"student":11561,"lesson_info":{"id":11358,"subject":554,"teacher":1115,"class":719},"presence":0,"period":216,"date":"2018-01-24"},{"id":851710,"mark":5,"student":11561,"lesson_info":{"id":11358,"subject":554,"teacher":1115,"class":719},"presence":0,"period":216,"date":"2018-01-31"},{"id":851711,"mark":5,"student":11561,"lesson_info":{"id":11358,"subject":554,"teacher":1115,"class":719},"presence":0,"period":216,"date":"2018-02-07"},{"id":851712,"mark":4,"student":11561,"lesson_info":{"id":11358,"subject":554,"teacher":1115,"class":719},"presence":0,"period":216,"date":"2018-02-14"},{"id":851713,"mark":5,"student":11561,"lesson_info":{"id":11358,"subject":554,"teacher":1115,"class":719},"presence":0,"period":216,"date":"2018-02-21"},{"id":851714,"mark":5,"student":11561,"lesson_info":{"id":11358,"subject":554,"teacher":1115,"class":719},"presence":0,"period":216,"date":"2018-02-28"},{"id":851715,"mark":null,"student":11561,"lesson_info":{"id":11358,"subject":554,"teacher":1115,"class":719},"presence":1,"period":216,"date":"2018-03-07"},{"id":851716,"mark":null,"student":11561,"lesson_info":{"id":11358,"subject":554,"teacher":1115,"class":719},"presence":1,"period":216,"date":"2018-03-07"},{"id":851717,"mark":5,"student":11561,"lesson_info":{"id":11358,"subject":554,"teacher":1115,"class":719},"presence":0,"period":216,"date":"2018-03-14"},{"id":851718,"mark":5,"student":11561,"lesson_info":{"id":11358,"subject":554,"teacher":1115,"class":719},"presence":0,"period":216,"date":"2018-03-21"},{"id":851719,"mark":5,"student":11561,"lesson_info":{"id":11358,"subject":554,"teacher":1115,"class":719},"presence":0,"period":216,"date":"2018-04-04"},{"id":851720,"mark":5,"student":11561,"lesson_info":{"id":11358,"subject":554,"teacher":1115,"class":719},"presence":0,"period":216,"date":"2018-04-11"},{"id":851721,"mark":4,"student":11561,"lesson_info":{"id":11358,"subject":554,"teacher":1115,"class":719},"presence":0,"period":216,"date":"2018-04-18"},{"id":851722,"mark":5,"student":11561,"lesson_info":{"id":11358,"subject":554,"teacher":1115,"class":719},"presence":0,"period":216,"date":"2018-04-25"},{"id":851723,"mark":4,"student":11561,"lesson_info":{"id":11358,"subject":554,"teacher":1115,"class":719},"presence":0,"period":216,"date":"2018-05-02"},{"id":851724,"mark":5,"student":11561,"lesson_info":{"id":11358,"subject":554,"teacher":1115,"class":719},"presence":0,"period":216,"date":"2018-05-11"},{"id":851725,"mark":4,"student":11561,"lesson_info":{"id":11358,"subject":554,"teacher":1115,"class":719},"presence":0,"period":216,"date":"2018-05-16"},{"id":851726,"mark":5,"student":11561,"lesson_info":{"id":11358,"subject":554,"teacher":1115,"class":719},"presence":0,"period":216,"date":"2018-05-23"}],"semester_marks":[{"id":70317,"mark":4,"student":11561,"lesson_info":{"id":11342,"subject":532,"teacher":1122,"class":719},"period":215},{"id":70318,"mark":4,"student":11561,"lesson_info":{"id":11342,"subject":532,"teacher":1122,"class":719},"period":216},{"id":70355,"mark":4,"student":11561,"lesson_info":{"id":11343,"subject":524,"teacher":1153,"class":719},"period":215},{"id":70356,"mark":4,"student":11561,"lesson_info":{"id":11343,"subject":524,"teacher":1153,"class":719},"period":216},{"id":70393,"mark":5,"student":11561,"lesson_info":{"id":11344,"subject":526,"teacher":1134,"class":719},"period":215},{"id":70394,"mark":5,"student":11561,"lesson_info":{"id":11344,"subject":526,"teacher":1134,"class":719},"period":216},{"id":70431,"mark":5,"student":11561,"lesson_info":{"id":11345,"subject":527,"teacher":1136,"class":719},"period":215},{"id":70432,"mark":5,"student":11561,"lesson_info":{"id":11345,"subject":527,"teacher":1136,"class":719},"period":216},{"id":70469,"mark":4,"student":11561,"lesson_info":{"id":11346,"subject":533,"teacher":1122,"class":719},"period":215},{"id":70470,"mark":4,"student":11561,"lesson_info":{"id":11346,"subject":533,"teacher":1122,"class":719},"period":216},{"id":70507,"mark":5,"student":11561,"lesson_info":{"id":11347,"subject":528,"teacher":1115,"class":719},"period":215},{"id":70508,"mark":5,"student":11561,"lesson_info":{"id":11347,"subject":528,"teacher":1115,"class":719},"period":216},{"id":70545,"mark":4,"student":11561,"lesson_info":{"id":11348,"subject":529,"teacher":1065,"class":719},"period":215},{"id":70546,"mark":4,"student":11561,"lesson_info":{"id":11348,"subject":529,"teacher":1065,"class":719},"period":216},{"id":70583,"mark":5,"student":11561,"lesson_info":{"id":11349,"subject":535,"teacher":1082,"class":719},"period":215},{"id":70584,"mark":5,"student":11561,"lesson_info":{"id":11349,"subject":535,"teacher":1082,"class":719},"period":216},{"id":70621,"mark":4,"student":11561,"lesson_info":{"id":11350,"subject":530,"teacher":1065,"class":719},"period":215},{"id":70622,"mark":5,"student":11561,"lesson_info":{"id":11350,"subject":530,"teacher":1065,"class":719},"period":216},{"id":70652,"mark":4,"student":11561,"lesson_info":{"id":11351,"subject":546,"teacher":1073,"class":719},"period":216},{"id":70678,"mark":5,"student":11561,"lesson_info":{"id":11352,"subject":531,"teacher":1068,"class":719},"period":215},{"id":70679,"mark":5,"student":11561,"lesson_info":{"id":11352,"subject":531,"teacher":1068,"class":719},"period":216},{"id":70716,"mark":4,"student":11561,"lesson_info":{"id":11353,"subject":514,"teacher":1068,"class":719},"period":215},{"id":70717,"mark":4,"student":11561,"lesson_info":{"id":11353,"subject":514,"teacher":1068,"class":719},"period":216},{"id":70754,"mark":4,"student":11561,"lesson_info":{"id":11354,"subject":534,"teacher":1080,"class":719},"period":215},{"id":70755,"mark":4,"student":11561,"lesson_info":{"id":11354,"subject":534,"teacher":1080,"class":719},"period":216},{"id":70792,"mark":5,"student":11561,"lesson_info":{"id":11355,"subject":515,"teacher":1102,"class":719},"period":215},{"id":70793,"mark":5,"student":11561,"lesson_info":{"id":11355,"subject":515,"teacher":1102,"class":719},"period":216},{"id":70830,"mark":5,"student":11561,"lesson_info":{"id":11356,"subject":536,"teacher":1081,"class":719},"period":215},{"id":70831,"mark":5,"student":11561,"lesson_info":{"id":11356,"subject":536,"teacher":1081,"class":719},"period":216},{"id":70868,"mark":5,"student":11561,"lesson_info":{"id":11357,"subject":516,"teacher":1065,"class":719},"period":215},{"id":70869,"mark":5,"student":11561,"lesson_info":{"id":11357,"subject":516,"teacher":1065,"class":719},"period":216},{"id":70906,"mark":5,"student":11561,"lesson_info":{"id":11358,"subject":554,"teacher":1115,"class":719},"period":215},{"id":70907,"mark":5,"student":11561,"lesson_info":{"id":11358,"subject":554,"teacher":1115,"class":719},"period":216},{"id":70944,"mark":5,"student":11561,"lesson_info":{"id":11359,"subject":518,"teacher":1097,"class":719},"period":215},{"id":70945,"mark":5,"student":11561,"lesson_info":{"id":11359,"subject":518,"teacher":1097,"class":719},"period":216},{"id":70975,"mark":5,"student":11561,"lesson_info":{"id":11362,"subject":567,"teacher":1179,"class":719},"period":215}],"terminal_marks":[{"id":22173,"mark":4,"student":11561,"lesson_info":{"id":11342,"subject":532,"teacher":1122,"class":719},"year":2017,"type":1},{"id":22174,"mark":4,"student":11561,"lesson_info":{"id":11342,"subject":532,"teacher":1122,"class":719},"year":2017,"type":3},{"id":22204,"mark":4,"student":11561,"lesson_info":{"id":11343,"subject":524,"teacher":1153,"class":719},"year":2017,"type":1},{"id":22223,"mark":5,"student":11561,"lesson_info":{"id":11344,"subject":526,"teacher":1134,"class":719},"year":2017,"type":1},{"id":22242,"mark":5,"student":11561,"lesson_info":{"id":11345,"subject":527,"teacher":1136,"class":719},"year":2017,"type":1},{"id":22261,"mark":4,"student":11561,"lesson_info":{"id":11346,"subject":533,"teacher":1122,"class":719},"year":2017,"type":1},{"id":22280,"mark":5,"student":11561,"lesson_info":{"id":11347,"subject":528,"teacher":1115,"class":719},"year":2017,"type":1},{"id":22299,"mark":4,"student":11561,"lesson_info":{"id":11348,"subject":529,"teacher":1065,"class":719},"year":2017,"type":1},{"id":22318,"mark":5,"student":11561,"lesson_info":{"id":11349,"subject":535,"teacher":1082,"class":719},"year":2017,"type":1},{"id":22337,"mark":5,"student":11561,"lesson_info":{"id":11350,"subject":530,"teacher":1065,"class":719},"year":2017,"type":1},{"id":22356,"mark":4,"student":11561,"lesson_info":{"id":11351,"subject":546,"teacher":1073,"class":719},"year":2017,"type":1},{"id":22375,"mark":5,"student":11561,"lesson_info":{"id":11352,"subject":531,"teacher":1068,"class":719},"year":2017,"type":1},{"id":22401,"mark":4,"student":11561,"lesson_info":{"id":11353,"subject":514,"teacher":1068,"class":719},"year":2017,"type":1},{"id":22402,"mark":4,"student":11561,"lesson_info":{"id":11353,"subject":514,"teacher":1068,"class":719},"year":2017,"type":3},{"id":22432,"mark":4,"student":11561,"lesson_info":{"id":11354,"subject":534,"teacher":1080,"class":719},"year":2017,"type":1},{"id":22451,"mark":5,"student":11561,"lesson_info":{"id":11355,"subject":515,"teacher":1102,"class":719},"year":2017,"type":1},{"id":22470,"mark":5,"student":11561,"lesson_info":{"id":11356,"subject":536,"teacher":1081,"class":719},"year":2017,"type":1},{"id":22489,"mark":5,"student":11561,"lesson_info":{"id":11357,"subject":516,"teacher":1065,"class":719},"year":2017,"type":1},{"id":22508,"mark":5,"student":11561,"lesson_info":{"id":11358,"subject":554,"teacher":1115,"class":719},"year":2017,"type":1},{"id":22527,"mark":5,"student":11561,"lesson_info":{"id":11359,"subject":518,"teacher":1097,"class":719},"year":2017,"type":1}],"subjects":[{"id":514,"name":"Рус. язык","type":"Русский язык и литература","dnevnik_id":3000000000000001},{"id":515,"name":"Физкультура","type":"Неизвестно","dnevnik_id":3000000000000002},{"id":516,"name":"Кубановедение","type":"Прочее","dnevnik_id":3000000000000003},{"id":518,"name":"Шахматы","type":"Прочее","dnevnik_id":3000000000000005},{"id":524,"name":"Англ. язык","type":"Иностранный язык","dnevnik_id":3000000000000011},{"id":526,"name":"Биология","type":"Естествознание","dnevnik_id":3000000000000013},{"id":527,"name":"География","type":"Социальные науки","dnevnik_id":3000000000000014},{"id":528,"name":"Информатика","type":"Технология","dnevnik_id":3000000000000015},{"id":529,"name":"История","type":"Социальные науки","dnevnik_id":3000000000000016},{"id":530,"name":"Обществознание","type":"Социальные науки","dnevnik_id":3000000000000017},{"id":531,"name":"Литература","type":"Русский язык и литература","dnevnik_id":3000000000000018},{"id":532,"name":"Алгебра","type":"Математика","dnevnik_id":3000000000000019},{"id":533,"name":"Геометрия","type":"Математика","dnevnik_id":3000000000000020},{"id":534,"name":"Физика","type":"Естествознание","dnevnik_id":3000000000000021},{"id":535,"name":"ОБЖ","type":"Физическая культура","dnevnik_id":3000000000000022},{"id":536,"name":"Химия","type":"Естествознание","dnevnik_id":3000000000000023},{"id":546,"name":"Конст. право","type":"Социальные науки","dnevnik_id":3000000000000033},{"id":554,"name":"ИКТ","type":"Технология","dnevnik_id":3000000000000041},{"id":555,"name":"Математика (Э)","type":"Элективы","dnevnik_id":3000000000000042},{"id":567,"name":"экономика/право","type":"Социальные науки","dnevnik_id":3000000000000054}],"teachers":[{"id":1065,"full_name":"Порфирьева Шерил Изотовна","birthday":"1975-12-09","tel":null,"email":null,"dnevnik_id":1000000000003,"dnevnik_person_id":1000000000003,"job":"Учитель, Редактор"},{"id":1068,"full_name":"Олсуфьева Русалина Петровна","birthday":"1992-06-12","tel":null,"email":null,"dnevnik_id":1000000000006,"dnevnik_person_id":1000000000006,"job":"Учитель, Редактор"},{"id":1073,"full_name":"Аврамов Федот Феоктистович","birthday":"1974-12-17","tel":null,"email":null,"dnevnik_id":1000000000011,"dnevnik_person_id":1000000000011,"job":"Учитель"},{"id":1080,"full_name":"Максимова Инесса Владленовна","birthday":"1992-08-24","tel":null,"email":null,"dnevnik_id":1000000000018,"dnevnik_person_id":1000000000018,"job":"Учитель, Редактор"},{"id":1081,"full_name":"Софроньева Фатима Ефремовна","birthday":"2008-07-18","tel":"+7-(972)-957-36-48","email":"ireland1888@live.com","dnevnik_id":1000000000019,"dnevnik_person_id":1000000000019,"job":"Учитель, Редактор"},{"id":1082,"full_name":"Вильмонт Магистриан Ермолаевич","birthday":"1992-01-25","tel":null,"email":null,"dnevnik_id":1000000000020,"dnevnik_person_id":1000000000020,"job":"Учитель, Редактор"},{"id":1097,"full_name":"Безрученко Никита Герасимович","birthday":"2009-01-21","tel":null,"email":null,"dnevnik_id":1000000000034,"dnevnik_person_id":1000000000035,"job":"Учитель, Редактор"},{"id":1102,"full_name":"Вахтин Нестор Адамович","birthday":"2008-02-03","tel":null,"email":null,"dnevnik_id":1000000000038,"dnevnik_person_id":1000000000040,"job":"Учитель"},{"id":1115,"full_name":"Подколзина Вита Трифоновна","birthday":"1992-02-13","tel":null,"email":null,"dnevnik_id":1000000000050,"dnevnik_person_id":1000000000053,"job":"Учитель, Редактор"},{"id":1122,"full_name":"Соболева Заира Устиновна","birthday":"1992-09-03","tel":null,"email":null,"dnevnik_id":1000000000057,"dnevnik_person_id":1000000000060,"job":"Учитель, Редактор"},{"id":1134,"full_name":"Козлачкова Виола Тихоновна","birthday":"1987-08-19","tel":null,"email":null,"dnevnik_id":1000000000068,"dnevnik_person_id":1000000000072,"job":"Учитель, Редактор"},{"id":1136,"full_name":"Сальников Аникита Жанович","birthday":"1992-10-09","tel":null,"email":null,"dnevnik_id":1000000000069,"dnevnik_person_id":1000000000074,"job":"Учитель, Редактор"},{"id":1153,"full_name":"Нахапетова Кира Чеславовна","birthday":"2009-09-30","tel":null,"email":null,"dnevnik_id":1000000000084,"dnevnik_person_id":1000000000091,"job":null},{"id":1179,"full_name":"Зикунова Анита Евстигнеевна","birthday":null,"tel":null,"email":null,"dnevnik_id":1000000000109,"dnevnik_person_id":null,"job":null}],"periods":[{"id":215,"num":1,"year":2017,"dnevnik_id":1000000000000000017},{"id":216,"num":2,"year":2017,"dnevnik_id":1000000000000000018}]}}